<afdxxml name="test project">
    <resources>
        <switch name="switch1" number="1" ports="1,2,3" x="298.5" y="249.5"/>
        <switch name="switch2" number="2" ports="4,5,6" x="405.5" y="248.5"/>
        <endSystem name="endSystem1" number="3" ports="7" x="234.5" y="175.5"/>
        <endSystem name="endSystem2" number="4" ports="8" x="234.5" y="323.5"/>
        <endSystem name="endSystem3" number="5" ports="9" x="489.5" y="158.5"/>
        <endSystem name="endSystem4" number="6" ports="10" x="500.5" y="322.5"/>
        <partition connectedTo="3" name="partition1" number="7" x="224.5" y="105.5"/>
        <partition connectedTo="3" name="partition2" number="8" x="158.5" y="174.5"/>
        <partition connectedTo="4" name="partition3" number="9" x="162.5" y="319.5"/>
        <partition connectedTo="4" name="partition4" number="10" x="233.5" y="409.5"/>
        <partition connectedTo="5" name="partition5" number="11" x="481.5" y="82.5"/>
        <partition connectedTo="5" name="partition6" number="12" x="570.5" y="153.5"/>
        <partition connectedTo="6" name="partition7" number="13" x="580.5" y="313.5"/>
        <partition connectedTo="6" name="partition8" number="14" x="504.5" y="400.5"/>
        <link capacity="12500" from="1" fromType="0" to="4" toType="0"/>
        <link capacity="12500" from="7" fromType="0" to="2" toType="0"/>
        <link capacity="12500" from="8" fromType="0" to="3" toType="0"/>
        <link capacity="12500" from="9" fromType="0" to="5" toType="0"/>
        <link capacity="12500" from="10" fromType="0" to="6" toType="0"/>
    </resources>
    <virtualLinks>
        <virtualLink bag="128" dest="3" id="Designed for Data Flow 1" lmax="1467" number="1" responseTime="3476" source="4" lmin="64">
            <path dest="3" path="3,7" source="4"/>
        </virtualLink>
        <virtualLink bag="64" dest="5" id="Designed for Data Flow 2" lmax="843" number="2" responseTime="4349" source="3" lmin="64">
            <path dest="5" path="2,4,9" source="3"/>
        </virtualLink>
        <virtualLink bag="32" dest="4,6" id="Designed for Data Flow 3" lmax="809" number="3" responseTime="5471" source="5" lmin="64">
            <path dest="4" path="5,1,8" source="5"/>
            <path dest="6" path="5,10" source="5"/>
        </virtualLink>
        <virtualLink bag="32" dest="3,5" id="Designed for Data Flow 4" lmax="838" number="4" responseTime="4984" source="6" lmin="64">
            <path dest="3" path="6,1,7" source="6"/>
            <path dest="5" path="6,9" source="6"/>
        </virtualLink>
        <virtualLink bag="16" dest="3,4,5" id="Designed for Data Flow 5" lmax="1162" number="5" responseTime="4984" source="6" lmin="64">
            <path dest="3" path="6,1,7" source="6"/>
            <path dest="4" path="6,1,8" source="6"/>
            <path dest="5" path="6,9" source="6"/>
        </virtualLink>
        <virtualLink bag="128" dest="3,4" id="Designed for Data Flow 6" lmax="1036" number="6" responseTime="4984" source="6" lmin="64">
            <path dest="3" path="6,1,7" source="6"/>
            <path dest="4" path="6,1,8" source="6"/>
        </virtualLink>
        <virtualLink bag="128" dest="3,5,6" id="Designed for Data Flow 7" lmax="561" number="7" responseTime="4735" source="4" lmin="64">
            <path dest="3" path="3,7" source="4"/>
            <path dest="5" path="3,4,9" source="4"/>
            <path dest="6" path="3,4,10" source="4"/>
        </virtualLink>
        <virtualLink bag="32" dest="6" id="Designed for Data Flow 8" lmax="910" number="8" responseTime="3973" source="5" lmin="64">
            <path dest="6" path="5,10" source="5"/>
        </virtualLink>
        <virtualLink bag="128" dest="6" id="Designed for Data Flow 9" lmax="685" number="9" responseTime="4735" source="4" lmin="64">
            <path dest="6" path="3,4,10" source="4"/>
        </virtualLink>
        <virtualLink bag="32" dest="5" id="Designed for Data Flow 10" lmax="1067" number="10" responseTime="4485" source="4" lmin="64">
            <path dest="5" path="3,4,9" source="4"/>
        </virtualLink>
        <virtualLink bag="128" dest="3,6" id="Designed for Data Flow 11" lmax="282" number="11" responseTime="4735" source="4" lmin="64">
            <path dest="3" path="3,7" source="4"/>
            <path dest="6" path="3,4,10" source="4"/>
        </virtualLink>
        <virtualLink bag="32" dest="3,4" id="Designed for Data Flow 12" lmax="1237" number="12" responseTime="5776" source="5" lmin="64">
            <path dest="3" path="5,1,7" source="5"/>
            <path dest="4" path="5,1,8" source="5"/>
        </virtualLink>
        <virtualLink bag="128" dest="3,5" id="Designed for Data Flow 13" lmax="382" number="13" responseTime="4984" source="6" lmin="64">
            <path dest="3" path="6,1,7" source="6"/>
            <path dest="5" path="6,9" source="6"/>
        </virtualLink>
        <virtualLink bag="128" dest="3" id="Designed for Data Flow 14" lmax="1337" number="14" responseTime="3476" source="4" lmin="64">
            <path dest="3" path="3,7" source="4"/>
        </virtualLink>
        <virtualLink bag="64" dest="3" id="Designed for Data Flow 15" lmax="1203" number="15" responseTime="3476" source="4" lmin="64">
            <path dest="3" path="3,7" source="4"/>
        </virtualLink>
        <virtualLink bag="64" dest="6" id="Designed for Data Flow 16" lmax="848" number="16" responseTime="3974" source="5" lmin="64">
            <path dest="6" path="5,10" source="5"/>
        </virtualLink>
        <virtualLink bag="32" dest="3,6" id="Designed for Data Flow 17" lmax="1030" number="17" responseTime="5776" source="5" lmin="64">
            <path dest="3" path="5,1,7" source="5"/>
            <path dest="6" path="5,10" source="5"/>
        </virtualLink>
        <virtualLink bag="64" dest="3,4" id="Designed for Data Flow 18" lmax="1115" number="18" responseTime="5776" source="5" lmin="64">
            <path dest="3" path="5,1,7" source="5"/>
            <path dest="4" path="5,1,8" source="5"/>
        </virtualLink>
        <virtualLink bag="64" dest="5" id="Designed for Data Flow 19" lmax="902" number="19" responseTime="4486" source="4" lmin="64">
            <path dest="5" path="3,4,9" source="4"/>
        </virtualLink>
        <virtualLink bag="16" dest="6" id="Designed for Data Flow 20" lmax="1109" number="20" responseTime="4599" source="3" lmin="64">
            <path dest="6" path="2,4,10" source="3"/>
        </virtualLink>
        <virtualLink bag="64" dest="3" id="Designed for Data Flow 21" lmax="716" number="21" responseTime="4984" source="6" lmin="64">
            <path dest="3" path="6,1,7" source="6"/>
        </virtualLink>
        <virtualLink bag="64" dest="4,6" id="Designed for Data Flow 22" lmax="1294" number="22" responseTime="5471" source="5" lmin="64">
            <path dest="4" path="5,1,8" source="5"/>
            <path dest="6" path="5,10" source="5"/>
        </virtualLink>
        <virtualLink bag="128" dest="3,4,6" id="Designed for Data Flow 23" lmax="1390" number="23" responseTime="5776" source="5" lmin="64">
            <path dest="3" path="5,1,7" source="5"/>
            <path dest="4" path="5,1,8" source="5"/>
            <path dest="6" path="5,10" source="5"/>
        </virtualLink>
        <virtualLink bag="128" dest="5,6" id="Designed for Data Flow 24" lmax="1422" number="24" responseTime="4735" source="4" lmin="64">
            <path dest="5" path="3,4,9" source="4"/>
            <path dest="6" path="3,4,10" source="4"/>
        </virtualLink>
        <virtualLink bag="128" dest="4,5" id="Designed for Data Flow 25" lmax="1072" number="25" responseTime="4350" source="3" lmin="64">
            <path dest="4" path="2,8" source="3"/>
            <path dest="5" path="2,4,9" source="3"/>
        </virtualLink>
        <virtualLink bag="16" dest="3,6" id="Designed for Data Flow 26" lmax="712" number="26" responseTime="4735" source="4" lmin="64">
            <path dest="3" path="3,7" source="4"/>
            <path dest="6" path="3,4,10" source="4"/>
        </virtualLink>
        <virtualLink bag="16" dest="3,6" id="Designed for Data Flow 27" lmax="825" number="27" responseTime="4735" source="4" lmin="64">
            <path dest="3" path="3,7" source="4"/>
            <path dest="6" path="3,4,10" source="4"/>
        </virtualLink>
        <virtualLink bag="128" dest="5" id="Designed for Data Flow 28" lmax="134" number="28" responseTime="2932" source="6" lmin="64">
            <path dest="5" path="6,9" source="6"/>
        </virtualLink>
        <virtualLink bag="128" dest="3,6" id="Designed for Data Flow 29" lmax="950" number="29" responseTime="5776" source="5" lmin="64">
            <path dest="3" path="5,1,7" source="5"/>
            <path dest="6" path="5,10" source="5"/>
        </virtualLink>
        <virtualLink bag="64" dest="3" id="Designed for Data Flow 30" lmax="808" number="30" responseTime="4985" source="6" lmin="64">
            <path dest="3" path="6,1,7" source="6"/>
        </virtualLink>
        <virtualLink bag="64" dest="5" id="Designed for Data Flow 31" lmax="738" number="31" responseTime="4349" source="3" lmin="64">
            <path dest="5" path="2,4,9" source="3"/>
        </virtualLink>
        <virtualLink bag="128" dest="4" id="Designed for Data Flow 32" lmax="1471" number="32" responseTime="5471" source="5" lmin="64">
            <path dest="4" path="5,1,8" source="5"/>
        </virtualLink>
        <virtualLink bag="128" dest="3,4,6" id="Designed for Data Flow 33" lmax="661" number="33" responseTime="5776" source="5" lmin="64">
            <path dest="3" path="5,1,7" source="5"/>
            <path dest="4" path="5,1,8" source="5"/>
            <path dest="6" path="5,10" source="5"/>
        </virtualLink>
        <virtualLink bag="2" dest="3" id="Designed for Data Flow 34" lmax="972" number="34" responseTime="5777" source="5" lmin="64">
            <path dest="3" path="5,1,7" source="5"/>
        </virtualLink>
        <virtualLink bag="128" dest="5" id="Designed for Data Flow 35" lmax="1422" number="35" responseTime="4486" source="4" lmin="64">
            <path dest="5" path="3,4,9" source="4"/>
        </virtualLink>
        <virtualLink bag="128" dest="3,5" id="Designed for Data Flow 36" lmax="851" number="36" responseTime="4984" source="6" lmin="64">
            <path dest="3" path="6,1,7" source="6"/>
            <path dest="5" path="6,9" source="6"/>
        </virtualLink>
        <virtualLink bag="128" dest="4,5" id="Designed for Data Flow 37" lmax="1051" number="37" responseTime="4678" source="6" lmin="64">
            <path dest="4" path="6,1,8" source="6"/>
            <path dest="5" path="6,9" source="6"/>
        </virtualLink>
        <virtualLink bag="64" dest="3,6" id="Designed for Data Flow 38" lmax="814" number="38" responseTime="4736" source="4" lmin="64">
            <path dest="3" path="3,7" source="4"/>
            <path dest="6" path="3,4,10" source="4"/>
        </virtualLink>
        <virtualLink bag="128" dest="4" id="Designed for Data Flow 39" lmax="1242" number="39" responseTime="3034" source="3" lmin="64">
            <path dest="4" path="2,8" source="3"/>
        </virtualLink>
        <virtualLink bag="128" dest="6" id="Designed for Data Flow 40" lmax="165" number="40" responseTime="4599" source="3" lmin="64">
            <path dest="6" path="2,4,10" source="3"/>
        </virtualLink>
        <virtualLink bag="128" dest="4" id="Designed for Data Flow 41" lmax="778" number="41" responseTime="3034" source="3" lmin="64">
            <path dest="4" path="2,8" source="3"/>
        </virtualLink>
        <virtualLink bag="128" dest="6" id="Designed for Data Flow 42" lmax="786" number="42" responseTime="3973" source="5" lmin="64">
            <path dest="6" path="5,10" source="5"/>
        </virtualLink>
        <virtualLink bag="128" dest="3,5" id="Designed for Data Flow 43" lmax="1294" number="43" responseTime="4984" source="6" lmin="64">
            <path dest="3" path="6,1,7" source="6"/>
            <path dest="5" path="6,9" source="6"/>
        </virtualLink>
        <virtualLink bag="32" dest="4,5" id="Designed for Data Flow 44" lmax="142" number="44" responseTime="4678" source="6" lmin="64">
            <path dest="4" path="6,1,8" source="6"/>
            <path dest="5" path="6,9" source="6"/>
        </virtualLink>
        <virtualLink bag="128" dest="3,4" id="Designed for Data Flow 45" lmax="890" number="45" responseTime="4984" source="6" lmin="64">
            <path dest="3" path="6,1,7" source="6"/>
            <path dest="4" path="6,1,8" source="6"/>
        </virtualLink>
        <virtualLink bag="128" dest="4" id="Designed for Data Flow 46" lmax="1129" number="46" responseTime="5470" source="5" lmin="64">
            <path dest="4" path="5,1,8" source="5"/>
        </virtualLink>
        <virtualLink bag="32" dest="3,6" id="Designed for Data Flow 47" lmax="814" number="47" responseTime="4736" source="4" lmin="64">
            <path dest="3" path="3,7" source="4"/>
            <path dest="6" path="3,4,10" source="4"/>
        </virtualLink>
        <virtualLink bag="128" dest="3,4,5" id="Designed for Data Flow 48" lmax="1262" number="48" responseTime="4984" source="6" lmin="64">
            <path dest="3" path="6,1,7" source="6"/>
            <path dest="4" path="6,1,8" source="6"/>
            <path dest="5" path="6,9" source="6"/>
        </virtualLink>
        <virtualLink bag="16" dest="4,5" id="Designed for Data Flow 49" lmax="979" number="49" responseTime="4349" source="3" lmin="64">
            <path dest="4" path="2,8" source="3"/>
            <path dest="5" path="2,4,9" source="3"/>
        </virtualLink>
        <virtualLink bag="128" dest="3,4" id="Designed for Data Flow 50" lmax="870" number="50" responseTime="5776" source="5" lmin="64">
            <path dest="3" path="5,1,7" source="5"/>
            <path dest="4" path="5,1,8" source="5"/>
        </virtualLink>
        <virtualLink bag="128" dest="3,4,6" id="Designed for Data Flow 51" lmax="1061" number="51" responseTime="5776" source="5" lmin="64">
            <path dest="3" path="5,1,7" source="5"/>
            <path dest="4" path="5,1,8" source="5"/>
            <path dest="6" path="5,10" source="5"/>
        </virtualLink>
        <virtualLink bag="128" dest="4,6" id="Designed for Data Flow 52" lmax="1195" number="52" responseTime="4599" source="3" lmin="64">
            <path dest="4" path="2,8" source="3"/>
            <path dest="6" path="2,4,10" source="3"/>
        </virtualLink>
        <virtualLink bag="128" dest="3,6" id="Designed for Data Flow 53" lmax="1057" number="53" responseTime="4735" source="4" lmin="64">
            <path dest="3" path="3,7" source="4"/>
            <path dest="6" path="3,4,10" source="4"/>
        </virtualLink>
        <virtualLink bag="32" dest="5" id="Designed for Data Flow 54" lmax="902" number="54" responseTime="2931" source="6" lmin="64">
            <path dest="5" path="6,9" source="6"/>
        </virtualLink>
        <virtualLink bag="32" dest="3,5" id="Designed for Data Flow 55" lmax="1452" number="55" responseTime="4486" source="4" lmin="64">
            <path dest="3" path="3,7" source="4"/>
            <path dest="5" path="3,4,9" source="4"/>
        </virtualLink>
        <virtualLink bag="128" dest="3,4" id="Designed for Data Flow 56" lmax="934" number="56" responseTime="5777" source="5" lmin="64">
            <path dest="3" path="5,1,7" source="5"/>
            <path dest="4" path="5,1,8" source="5"/>
        </virtualLink>
        <virtualLink bag="16" dest="3,4" id="Designed for Data Flow 57" lmax="779" number="57" responseTime="4984" source="6" lmin="64">
            <path dest="3" path="6,1,7" source="6"/>
            <path dest="4" path="6,1,8" source="6"/>
        </virtualLink>
        <virtualLink bag="128" dest="4,6" id="Designed for Data Flow 58" lmax="1467" number="58" responseTime="5470" source="5" lmin="64">
            <path dest="4" path="5,1,8" source="5"/>
            <path dest="6" path="5,10" source="5"/>
        </virtualLink>
        <virtualLink bag="128" dest="5" id="Designed for Data Flow 59" lmax="761" number="59" responseTime="2931" source="6" lmin="64">
            <path dest="5" path="6,9" source="6"/>
        </virtualLink>
        <virtualLink bag="8" dest="4" id="Designed for Data Flow 60" lmax="1256" number="60" responseTime="3034" source="3" lmin="64">
            <path dest="4" path="2,8" source="3"/>
        </virtualLink>
        <virtualLink bag="128" dest="4" id="Designed for Data Flow 61" lmax="917" number="61" responseTime="5470" source="5" lmin="64">
            <path dest="4" path="5,1,8" source="5"/>
        </virtualLink>
        <virtualLink bag="32" dest="6" id="Designed for Data Flow 62" lmax="903" number="62" responseTime="4599" source="3" lmin="64">
            <path dest="6" path="2,4,10" source="3"/>
        </virtualLink>
        <virtualLink bag="64" dest="5" id="Designed for Data Flow 63" lmax="908" number="63" responseTime="4350" source="3" lmin="64">
            <path dest="5" path="2,4,9" source="3"/>
        </virtualLink>
        <virtualLink bag="4" dest="3,4,6" id="Designed for Data Flow 64" lmax="868" number="64" responseTime="5776" source="5" lmin="64">
            <path dest="3" path="5,1,7" source="5"/>
            <path dest="4" path="5,1,8" source="5"/>
            <path dest="6" path="5,10" source="5"/>
        </virtualLink>
        <virtualLink bag="64" dest="3" id="Designed for Data Flow 65" lmax="1362" number="65" responseTime="5776" source="5" lmin="64">
            <path dest="3" path="5,1,7" source="5"/>
        </virtualLink>
        <virtualLink bag="128" dest="3" id="Designed for Data Flow 66" lmax="458" number="66" responseTime="5777" source="5" lmin="64">
            <path dest="3" path="5,1,7" source="5"/>
        </virtualLink>
        <virtualLink bag="128" dest="4,5" id="Designed for Data Flow 67" lmax="1007" number="67" responseTime="4350" source="3" lmin="64">
            <path dest="4" path="2,8" source="3"/>
            <path dest="5" path="2,4,9" source="3"/>
        </virtualLink>
        <virtualLink bag="32" dest="3" id="Designed for Data Flow 68" lmax="1143" number="68" responseTime="5776" source="5" lmin="64">
            <path dest="3" path="5,1,7" source="5"/>
        </virtualLink>
        <virtualLink bag="16" dest="3,4" id="Designed for Data Flow 69" lmax="978" number="69" responseTime="5776" source="5" lmin="64">
            <path dest="3" path="5,1,7" source="5"/>
            <path dest="4" path="5,1,8" source="5"/>
        </virtualLink>
        <virtualLink bag="128" dest="3,6" id="Designed for Data Flow 70" lmax="614" number="70" responseTime="4736" source="4" lmin="64">
            <path dest="3" path="3,7" source="4"/>
            <path dest="6" path="3,4,10" source="4"/>
        </virtualLink>
        <virtualLink bag="64" dest="5" id="Designed for Data Flow 71" lmax="1051" number="71" responseTime="2931" source="6" lmin="64">
            <path dest="5" path="6,9" source="6"/>
        </virtualLink>
        <virtualLink bag="128" dest="3,5,6" id="Designed for Data Flow 72" lmax="1222" number="72" responseTime="4735" source="4" lmin="64">
            <path dest="3" path="3,7" source="4"/>
            <path dest="5" path="3,4,9" source="4"/>
            <path dest="6" path="3,4,10" source="4"/>
        </virtualLink>
        <virtualLink bag="64" dest="3,4" id="Designed for Data Flow 73" lmax="1046" number="73" responseTime="4985" source="6" lmin="64">
            <path dest="3" path="6,1,7" source="6"/>
            <path dest="4" path="6,1,8" source="6"/>
        </virtualLink>
        <virtualLink bag="128" dest="4,5,6" id="Designed for Data Flow 74" lmax="670" number="74" responseTime="4599" source="3" lmin="64">
            <path dest="4" path="2,8" source="3"/>
            <path dest="5" path="2,4,9" source="3"/>
            <path dest="6" path="2,4,10" source="3"/>
        </virtualLink>
        <virtualLink bag="128" dest="4" id="Designed for Data Flow 75" lmax="1016" number="75" responseTime="3034" source="3" lmin="64">
            <path dest="4" path="2,8" source="3"/>
        </virtualLink>
        <virtualLink bag="32" dest="6" id="Designed for Data Flow 76" lmax="893" number="76" responseTime="3973" source="5" lmin="64">
            <path dest="6" path="5,10" source="5"/>
        </virtualLink>
        <virtualLink bag="128" dest="4,5,6" id="Designed for Data Flow 77" lmax="796" number="77" responseTime="4599" source="3" lmin="64">
            <path dest="4" path="2,8" source="3"/>
            <path dest="5" path="2,4,9" source="3"/>
            <path dest="6" path="2,4,10" source="3"/>
        </virtualLink>
        <virtualLink bag="128" dest="3" id="Designed for Data Flow 78" lmax="251" number="78" responseTime="5776" source="5" lmin="64">
            <path dest="3" path="5,1,7" source="5"/>
        </virtualLink>
        <virtualLink bag="64" dest="3,6" id="Designed for Data Flow 79" lmax="868" number="79" responseTime="5776" source="5" lmin="64">
            <path dest="3" path="5,1,7" source="5"/>
            <path dest="6" path="5,10" source="5"/>
        </virtualLink>
        <virtualLink bag="64" dest="6" id="Designed for Data Flow 80" lmax="905" number="80" responseTime="4599" source="3" lmin="64">
            <path dest="6" path="2,4,10" source="3"/>
        </virtualLink>
        <virtualLink bag="128" dest="4,6" id="Designed for Data Flow 81" lmax="1189" number="81" responseTime="5470" source="5" lmin="64">
            <path dest="4" path="5,1,8" source="5"/>
            <path dest="6" path="5,10" source="5"/>
        </virtualLink>
        <virtualLink bag="32" dest="3,4" id="Designed for Data Flow 82" lmax="825" number="82" responseTime="4984" source="6" lmin="64">
            <path dest="3" path="6,1,7" source="6"/>
            <path dest="4" path="6,1,8" source="6"/>
        </virtualLink>
        <virtualLink bag="64" dest="5,6" id="Designed for Data Flow 83" lmax="1348" number="83" responseTime="4735" source="4" lmin="64">
            <path dest="5" path="3,4,9" source="4"/>
            <path dest="6" path="3,4,10" source="4"/>
        </virtualLink>
        <virtualLink bag="1" dest="3,6" id="Designed for Data Flow 84" lmax="1123" number="84" responseTime="4735" source="4" lmin="64">
            <path dest="3" path="3,7" source="4"/>
            <path dest="6" path="3,4,10" source="4"/>
        </virtualLink>
        <virtualLink bag="64" dest="3,5" id="Designed for Data Flow 85" lmax="1409" number="85" responseTime="4985" source="6" lmin="64">
            <path dest="3" path="6,1,7" source="6"/>
            <path dest="5" path="6,9" source="6"/>
        </virtualLink>
        <virtualLink bag="16" dest="4" id="Designed for Data Flow 86" lmax="1249" number="86" responseTime="5470" source="5" lmin="64">
            <path dest="4" path="5,1,8" source="5"/>
        </virtualLink>
        <virtualLink bag="128" dest="4,6" id="Designed for Data Flow 87" lmax="1149" number="87" responseTime="4599" source="3" lmin="64">
            <path dest="4" path="2,8" source="3"/>
            <path dest="6" path="2,4,10" source="3"/>
        </virtualLink>
        <virtualLink bag="64" dest="3,4,5" id="Designed for Data Flow 88" lmax="1369" number="88" responseTime="4984" source="6" lmin="64">
            <path dest="3" path="6,1,7" source="6"/>
            <path dest="4" path="6,1,8" source="6"/>
            <path dest="5" path="6,9" source="6"/>
        </virtualLink>
        <virtualLink bag="16" dest="4,5,6" id="Designed for Data Flow 89" lmax="845" number="89" responseTime="4599" source="3" lmin="64">
            <path dest="4" path="2,8" source="3"/>
            <path dest="5" path="2,4,9" source="3"/>
            <path dest="6" path="2,4,10" source="3"/>
        </virtualLink>
        <virtualLink bag="64" dest="5,6" id="Designed for Data Flow 90" lmax="1037" number="90" responseTime="4735" source="4" lmin="64">
            <path dest="5" path="3,4,9" source="4"/>
            <path dest="6" path="3,4,10" source="4"/>
        </virtualLink>
        <virtualLink bag="128" dest="3,4" id="Designed for Data Flow 91" lmax="635" number="91" responseTime="4985" source="6" lmin="64">
            <path dest="3" path="6,1,7" source="6"/>
            <path dest="4" path="6,1,8" source="6"/>
        </virtualLink>
        <virtualLink bag="64" dest="3,4" id="Designed for Data Flow 92" lmax="1187" number="92" responseTime="5776" source="5" lmin="64">
            <path dest="3" path="5,1,7" source="5"/>
            <path dest="4" path="5,1,8" source="5"/>
        </virtualLink>
        <virtualLink bag="64" dest="4,5,6" id="Designed for Data Flow 93" lmax="1205" number="93" responseTime="4599" source="3" lmin="64">
            <path dest="4" path="2,8" source="3"/>
            <path dest="5" path="2,4,9" source="3"/>
            <path dest="6" path="2,4,10" source="3"/>
        </virtualLink>
        <virtualLink bag="32" dest="4,5" id="Designed for Data Flow 94" lmax="668" number="94" responseTime="4349" source="3" lmin="64">
            <path dest="4" path="2,8" source="3"/>
            <path dest="5" path="2,4,9" source="3"/>
        </virtualLink>
        <virtualLink bag="128" dest="4,6" id="Designed for Data Flow 95" lmax="1326" number="95" responseTime="4599" source="3" lmin="64">
            <path dest="4" path="2,8" source="3"/>
            <path dest="6" path="2,4,10" source="3"/>
        </virtualLink>
        <virtualLink bag="128" dest="6" id="Designed for Data Flow 96" lmax="926" number="96" responseTime="3973" source="5" lmin="64">
            <path dest="6" path="5,10" source="5"/>
        </virtualLink>
        <virtualLink bag="128" dest="4" id="Designed for Data Flow 97" lmax="137" number="97" responseTime="3034" source="3" lmin="64">
            <path dest="4" path="2,8" source="3"/>
        </virtualLink>
        <virtualLink bag="128" dest="3,5,6" id="Designed for Data Flow 98" lmax="1250" number="98" responseTime="4735" source="4" lmin="64">
            <path dest="3" path="3,7" source="4"/>
            <path dest="5" path="3,4,9" source="4"/>
            <path dest="6" path="3,4,10" source="4"/>
        </virtualLink>
        <virtualLink bag="32" dest="4" id="Designed for Data Flow 99" lmax="919" number="99" responseTime="4679" source="6" lmin="64">
            <path dest="4" path="6,1,8" source="6"/>
        </virtualLink>
        <virtualLink bag="4" dest="4,5" id="Designed for Data Flow 100" lmax="1061" number="100" responseTime="4678" source="6" lmin="64">
            <path dest="4" path="6,1,8" source="6"/>
            <path dest="5" path="6,9" source="6"/>
        </virtualLink>
    </virtualLinks>
    <dataFlows>
        <dataFlow dest="8" id="Data Flow 1" jMax="0" msgSize="1420" period="266" source="10" tMax="300" vl="1"/>
        <dataFlow dest="12,11" id="Data Flow 2" jMax="0" msgSize="796" period="102" source="8" tMax="300" vl="2"/>
        <dataFlow dest="9,13" id="Data Flow 3" jMax="0" msgSize="3808" period="174" source="12" tMax="300" vl="3"/>
        <dataFlow dest="7,12" id="Data Flow 4" jMax="0" msgSize="3163" period="140" source="14" tMax="300" vl="4"/>
        <dataFlow dest="12,8,9" id="Data Flow 5" jMax="0" msgSize="3345" period="58" source="13" tMax="300" vl="5"/>
        <dataFlow dest="10,7" id="Data Flow 6" jMax="0" msgSize="2967" period="493" source="14" tMax="300" vl="6"/>
        <dataFlow dest="11,13,7" id="Data Flow 7" jMax="0" msgSize="1541" period="426" source="9" tMax="300" vl="7"/>
        <dataFlow dest="14" id="Data Flow 8" jMax="0" msgSize="2587" period="99" source="11" tMax="300" vl="8"/>
        <dataFlow dest="14" id="Data Flow 9" jMax="0" msgSize="1914" period="496" source="10" tMax="300" vl="9"/>
        <dataFlow dest="11" id="Data Flow 10" jMax="0" msgSize="3060" period="103" source="10" tMax="300" vl="10"/>
        <dataFlow dest="13,8,7" id="Data Flow 11" jMax="0" msgSize="235" period="138" source="9" tMax="300" vl="11"/>
        <dataFlow dest="7,9" id="Data Flow 12" jMax="0" msgSize="3568" period="97" source="11" tMax="300" vl="12"/>
        <dataFlow dest="11,8" id="Data Flow 13" jMax="0" msgSize="335" period="238" source="13" tMax="300" vl="13"/>
        <dataFlow dest="8" id="Data Flow 14" jMax="0" msgSize="2580" period="308" source="10" tMax="300" vl="14"/>
        <dataFlow dest="7,8" id="Data Flow 15" jMax="0" msgSize="3467" period="206" source="9" tMax="300" vl="15"/>
        <dataFlow dest="14" id="Data Flow 16" jMax="0" msgSize="3203" period="279" source="11" tMax="300" vl="16"/>
        <dataFlow dest="7,14" id="Data Flow 17" jMax="0" msgSize="1965" period="91" source="11" tMax="300" vl="17"/>
        <dataFlow dest="8,9" id="Data Flow 18" jMax="0" msgSize="3203" period="219" source="11" tMax="300" vl="18"/>
        <dataFlow dest="11,12" id="Data Flow 19" jMax="0" msgSize="2564" period="200" source="10" tMax="300" vl="19"/>
        <dataFlow dest="14" id="Data Flow 20" jMax="0" msgSize="2124" period="46" source="7" tMax="300" vl="20"/>
        <dataFlow dest="8" id="Data Flow 21" jMax="0" msgSize="2005" period="216" source="13" tMax="300" vl="21"/>
        <dataFlow dest="14,13,10" id="Data Flow 22" jMax="0" msgSize="2493" period="130" source="12" tMax="300" vl="22"/>
        <dataFlow dest="9,7,14" id="Data Flow 23" jMax="0" msgSize="1343" period="131" source="11" tMax="300" vl="23"/>
        <dataFlow dest="12,14" id="Data Flow 24" jMax="0" msgSize="2750" period="316" source="10" tMax="300" vl="24"/>
        <dataFlow dest="10,11" id="Data Flow 25" jMax="0" msgSize="2050" period="288" source="7" tMax="300" vl="25"/>
        <dataFlow dest="14,8" id="Data Flow 26" jMax="0" msgSize="3325" period="83" source="9" tMax="300" vl="26"/>
        <dataFlow dest="14,7" id="Data Flow 27" jMax="0" msgSize="3109" period="73" source="9" tMax="300" vl="27"/>
        <dataFlow dest="12" id="Data Flow 28" jMax="0" msgSize="87" period="213" source="13" tMax="300" vl="28"/>
        <dataFlow dest="14,8,7" id="Data Flow 29" jMax="0" msgSize="903" period="405" source="12" tMax="300" vl="29"/>
        <dataFlow dest="8" id="Data Flow 30" jMax="0" msgSize="3805" period="352" source="14" tMax="300" vl="30"/>
        <dataFlow dest="12" id="Data Flow 31" jMax="0" msgSize="3451" period="357" source="7" tMax="300" vl="31"/>
        <dataFlow dest="9" id="Data Flow 32" jMax="0" msgSize="1424" period="209" source="12" tMax="300" vl="32"/>
        <dataFlow dest="13,7,9" id="Data Flow 33" jMax="0" msgSize="1840" period="480" source="11" tMax="300" vl="33"/>
        <dataFlow dest="7" id="Data Flow 34" jMax="0" msgSize="1850" period="4" source="12" tMax="300" vl="34"/>
        <dataFlow dest="11" id="Data Flow 35" jMax="0" msgSize="1375" period="431" source="10" tMax="300" vl="35"/>
        <dataFlow dest="12,8" id="Data Flow 36" jMax="0" msgSize="2410" period="399" source="14" tMax="300" vl="36"/>
        <dataFlow dest="12,9" id="Data Flow 37" jMax="0" msgSize="1004" period="290" source="14" tMax="300" vl="37"/>
        <dataFlow dest="14,8" id="Data Flow 38" jMax="0" msgSize="3067" period="296" source="10" tMax="300" vl="38"/>
        <dataFlow dest="9,10" id="Data Flow 39" jMax="0" msgSize="2389" period="319" source="8" tMax="300" vl="39"/>
        <dataFlow dest="13,14" id="Data Flow 40" jMax="0" msgSize="118" period="435" source="7" tMax="300" vl="40"/>
        <dataFlow dest="9" id="Data Flow 41" jMax="0" msgSize="2191" period="408" source="8" tMax="300" vl="41"/>
        <dataFlow dest="13" id="Data Flow 42" jMax="0" msgSize="2215" period="408" source="11" tMax="300" vl="42"/>
        <dataFlow dest="7,11,8" id="Data Flow 43" jMax="0" msgSize="1247" period="368" source="14" tMax="300" vl="43"/>
        <dataFlow dest="11,10" id="Data Flow 44" jMax="0" msgSize="95" period="62" source="13" tMax="300" vl="44"/>
        <dataFlow dest="8,10" id="Data Flow 45" jMax="0" msgSize="1686" period="285" source="13" tMax="300" vl="45"/>
        <dataFlow dest="9" id="Data Flow 46" jMax="0" msgSize="3246" period="417" source="11" tMax="300" vl="46"/>
        <dataFlow dest="13,8" id="Data Flow 47" jMax="0" msgSize="2301" period="124" source="9" tMax="300" vl="47"/>
        <dataFlow dest="11,10,7" id="Data Flow 48" jMax="0" msgSize="1215" period="209" source="14" tMax="300" vl="48"/>
        <dataFlow dest="11,10" id="Data Flow 49" jMax="0" msgSize="2795" period="60" source="7" tMax="300" vl="49"/>
        <dataFlow dest="9,7" id="Data Flow 50" jMax="0" msgSize="2467" period="475" source="11" tMax="300" vl="50"/>
        <dataFlow dest="9,7,13" id="Data Flow 51" jMax="0" msgSize="2028" period="312" source="12" tMax="300" vl="51"/>
        <dataFlow dest="9,13,14" id="Data Flow 52" jMax="0" msgSize="3443" period="487" source="7" tMax="300" vl="52"/>
        <dataFlow dest="14,13,8" id="Data Flow 53" jMax="0" msgSize="1010" period="353" source="10" tMax="300" vl="53"/>
        <dataFlow dest="12,11" id="Data Flow 54" jMax="0" msgSize="2564" period="96" source="14" tMax="300" vl="54"/>
        <dataFlow dest="7,12,11" id="Data Flow 55" jMax="0" msgSize="1405" period="63" source="10" tMax="300" vl="55"/>
        <dataFlow dest="10,8" id="Data Flow 56" jMax="0" msgSize="887" period="129" source="12" tMax="300" vl="56"/>
        <dataFlow dest="8,10" id="Data Flow 57" jMax="0" msgSize="3659" period="92" source="14" tMax="300" vl="57"/>
        <dataFlow dest="10,14" id="Data Flow 58" jMax="0" msgSize="2840" period="345" source="12" tMax="300" vl="58"/>
        <dataFlow dest="12" id="Data Flow 59" jMax="0" msgSize="2140" period="445" source="13" tMax="300" vl="59"/>
        <dataFlow dest="9" id="Data Flow 60" jMax="0" msgSize="3627" period="25" source="8" tMax="300" vl="60"/>
        <dataFlow dest="9,10" id="Data Flow 61" jMax="0" msgSize="870" period="171" source="12" tMax="300" vl="61"/>
        <dataFlow dest="13" id="Data Flow 62" jMax="0" msgSize="2568" period="108" source="8" tMax="300" vl="62"/>
        <dataFlow dest="11" id="Data Flow 63" jMax="0" msgSize="861" period="100" source="7" tMax="300" vl="63"/>
        <dataFlow dest="13,8,10" id="Data Flow 64" jMax="0" msgSize="1641" period="8" source="11" tMax="300" vl="64"/>
        <dataFlow dest="7" id="Data Flow 65" jMax="0" msgSize="1315" period="71" source="12" tMax="300" vl="65"/>
        <dataFlow dest="7" id="Data Flow 66" jMax="0" msgSize="411" period="213" source="12" tMax="300" vl="66"/>
        <dataFlow dest="9,12" id="Data Flow 67" jMax="0" msgSize="960" period="181" source="7" tMax="300" vl="67"/>
        <dataFlow dest="7" id="Data Flow 68" jMax="0" msgSize="3286" period="117" source="11" tMax="300" vl="68"/>
        <dataFlow dest="7,8,10" id="Data Flow 69" jMax="0" msgSize="1861" period="37" source="11" tMax="300" vl="69"/>
        <dataFlow dest="14,8" id="Data Flow 70" jMax="0" msgSize="567" period="179" source="9" tMax="300" vl="70"/>
        <dataFlow dest="11" id="Data Flow 71" jMax="0" msgSize="2008" period="178" source="14" tMax="300" vl="71"/>
        <dataFlow dest="11,8,13" id="Data Flow 72" jMax="0" msgSize="2349" period="355" source="10" tMax="300" vl="72"/>
        <dataFlow dest="8,9" id="Data Flow 73" jMax="0" msgSize="2995" period="217" source="14" tMax="300" vl="73"/>
        <dataFlow dest="10,14,12" id="Data Flow 74" jMax="0" msgSize="1867" period="434" source="7" tMax="300" vl="74"/>
        <dataFlow dest="9" id="Data Flow 75" jMax="0" msgSize="1938" period="258" source="8" tMax="300" vl="75"/>
        <dataFlow dest="13,14" id="Data Flow 76" jMax="0" msgSize="3381" period="134" source="11" tMax="300" vl="76"/>
        <dataFlow dest="10,12,13" id="Data Flow 77" jMax="0" msgSize="1497" period="316" source="8" tMax="300" vl="77"/>
        <dataFlow dest="7" id="Data Flow 78" jMax="0" msgSize="204" period="193" source="11" tMax="300" vl="78"/>
        <dataFlow dest="14,7" id="Data Flow 79" jMax="0" msgSize="3283" period="304" source="12" tMax="300" vl="79"/>
        <dataFlow dest="13" id="Data Flow 80" jMax="0" msgSize="3431" period="278" source="7" tMax="300" vl="80"/>
        <dataFlow dest="13,9" id="Data Flow 81" jMax="0" msgSize="2283" period="264" source="11" tMax="300" vl="81"/>
        <dataFlow dest="7,9" id="Data Flow 82" jMax="0" msgSize="2334" period="118" source="13" tMax="300" vl="82"/>
        <dataFlow dest="14,11" id="Data Flow 83" jMax="0" msgSize="1301" period="75" source="10" tMax="300" vl="83"/>
        <dataFlow dest="7,8,14" id="Data Flow 84" jMax="0" msgSize="2152" period="2" source="10" tMax="300" vl="84"/>
        <dataFlow dest="7,11" id="Data Flow 85" jMax="0" msgSize="2724" period="134" source="14" tMax="300" vl="85"/>
        <dataFlow dest="9,10" id="Data Flow 86" jMax="0" msgSize="3605" period="49" source="11" tMax="300" vl="86"/>
        <dataFlow dest="9,13,10" id="Data Flow 87" jMax="0" msgSize="2203" period="294" source="8" tMax="300" vl="87"/>
        <dataFlow dest="9,8,12" id="Data Flow 88" jMax="0" msgSize="1322" period="80" source="14" tMax="300" vl="88"/>
        <dataFlow dest="13,12,10" id="Data Flow 89" jMax="0" msgSize="1596" period="35" source="7" tMax="300" vl="89"/>
        <dataFlow dest="12,13" id="Data Flow 90" jMax="0" msgSize="3958" period="256" source="9" tMax="300" vl="90"/>
        <dataFlow dest="10,8" id="Data Flow 91" jMax="0" msgSize="588" period="377" source="13" tMax="300" vl="91"/>
        <dataFlow dest="9,8" id="Data Flow 92" jMax="0" msgSize="3418" period="210" source="11" tMax="300" vl="92"/>
        <dataFlow dest="14,12,9" id="Data Flow 93" jMax="0" msgSize="2315" period="164" source="8" tMax="300" vl="93"/>
        <dataFlow dest="12,9,11" id="Data Flow 94" jMax="0" msgSize="1862" period="112" source="7" tMax="300" vl="94"/>
        <dataFlow dest="9,10,14" id="Data Flow 95" jMax="0" msgSize="1279" period="490" source="7" tMax="300" vl="95"/>
        <dataFlow dest="13" id="Data Flow 96" jMax="0" msgSize="879" period="312" source="11" tMax="300" vl="96"/>
        <dataFlow dest="10" id="Data Flow 97" jMax="0" msgSize="90" period="298" source="8" tMax="300" vl="97"/>
        <dataFlow dest="12,13,8" id="Data Flow 98" jMax="0" msgSize="3609" period="459" source="10" tMax="300" vl="98"/>
        <dataFlow dest="9" id="Data Flow 99" jMax="0" msgSize="2615" period="114" source="13" tMax="300" vl="99"/>
        <dataFlow dest="9,12,11" id="Data Flow 100" jMax="0" msgSize="3040" period="15" source="14" tMax="300" vl="100"/>
    </dataFlows>
</afdxxml>
