<afdxxml name="test project">
    <resources>
        <switch name="switch1" number="1" ports="1,2,3,4" x="143.5" y="237.5"/>
        <switch name="switch2" number="2" ports="5,6,7,8" x="208.5" y="188.5"/>
        <switch name="switch3" number="3" ports="9,10,11,12" x="269.5" y="241.5"/>
        <switch name="switch4" number="4" ports="13,14,15,16" x="206.5" y="295.5"/>
        <endSystem name="endSystem1" number="5" ports="17" x="77.5" y="237.5"/>
        <endSystem name="endSystem2" number="6" ports="18" x="208.5" y="131.5"/>
        <endSystem name="endSystem3" number="7" ports="19" x="336.5" y="236.5"/>
        <endSystem name="endSystem4" number="8" ports="20" x="201.5" y="358.5"/>
        <partition connectedTo="5" name="partition1" number="9" x="18.5" y="236.5"/>
        <partition connectedTo="6" name="partition2" number="10" x="211.5" y="64.5"/>
        <partition connectedTo="7" name="partition3" number="11" x="403.5" y="237.5"/>
        <partition connectedTo="8" name="partition4" number="12" x="194.5" y="422.5"/>
        <link capacity="12500" from="1" fromType="0" to="5" toType="0"/>
        <link capacity="12500" from="6" fromType="0" to="9" toType="0"/>
        <link capacity="12500" from="10" fromType="0" to="13" toType="0"/>
        <link capacity="12500" from="14" fromType="0" to="2" toType="0"/>
        <link capacity="12500" from="3" fromType="0" to="11" toType="0"/>
        <link capacity="12500" from="7" fromType="0" to="15" toType="0"/>
        <link capacity="12500" from="4" fromType="0" to="17" toType="0"/>
        <link capacity="12500" from="8" fromType="0" to="18" toType="0"/>
        <link capacity="12500" from="12" fromType="0" to="19" toType="0"/>
        <link capacity="12500" from="16" fromType="0" to="20" toType="0"/>
    </resources>
    <virtualLinks>
        <virtualLink bag="128" dest="5,8" id="Designed for Data Flow 1" lmax="989" number="1" responseTime="4695" source="7" lmin="64">
            <path dest="5" path="12,3,17" source="7"/>
            <path dest="8" path="12,13,20" source="7"/>
        </virtualLink>
        <virtualLink bag="128" dest="8" id="Designed for Data Flow 2" lmax="711" number="2" responseTime="3886" source="6" lmin="64">
            <path dest="8" path="8,15,20" source="6"/>
        </virtualLink>
        <virtualLink bag="128" dest="6" id="Designed for Data Flow 3" lmax="1065" number="3" responseTime="5207" source="8" lmin="64">
            <path dest="6" path="16,7,18" source="8"/>
        </virtualLink>
        <virtualLink bag="128" dest="6,7,8" id="Designed for Data Flow 4" lmax="643" number="4" responseTime="5626" source="5" lmin="64">
            <path dest="6" path="4,5,18" source="5"/>
            <path dest="7" path="4,5,9,19" source="5"/>
            <path dest="8" path="4,5,9,13,20" source="5"/>
        </virtualLink>
        <virtualLink bag="128" dest="6,8" id="Designed for Data Flow 5" lmax="759" number="5" responseTime="4982" source="7" lmin="64">
            <path dest="6" path="12,6,18" source="7"/>
            <path dest="8" path="12,13,20" source="7"/>
        </virtualLink>
        <virtualLink bag="4" dest="5,6" id="Designed for Data Flow 6" lmax="897" number="6" responseTime="5683" source="7" lmin="64">
            <path dest="5" path="12,13,7,1,17" source="7"/>
            <path dest="6" path="12,13,7,18" source="7"/>
        </virtualLink>
        <virtualLink bag="128" dest="6,8" id="Designed for Data Flow 7" lmax="598" number="7" responseTime="5113" source="5" lmin="64">
            <path dest="6" path="4,5,18" source="5"/>
            <path dest="8" path="4,14,20" source="5"/>
        </virtualLink>
        <virtualLink bag="16" dest="5,7,8" id="Designed for Data Flow 8" lmax="693" number="8" responseTime="4276" source="6" lmin="64">
            <path dest="5" path="8,1,17" source="6"/>
            <path dest="7" path="8,9,19" source="6"/>
            <path dest="8" path="8,9,13,20" source="6"/>
        </virtualLink>
        <virtualLink bag="128" dest="5,6" id="Designed for Data Flow 9" lmax="1367" number="9" responseTime="4983" source="7" lmin="64">
            <path dest="5" path="12,3,17" source="7"/>
            <path dest="6" path="12,6,18" source="7"/>
        </virtualLink>
        <virtualLink bag="64" dest="6,7" id="Designed for Data Flow 10" lmax="603" number="10" responseTime="5112" source="5" lmin="64">
            <path dest="6" path="4,5,18" source="5"/>
            <path dest="7" path="4,5,9,19" source="5"/>
        </virtualLink>
        <virtualLink bag="64" dest="5,8" id="Designed for Data Flow 11" lmax="1104" number="11" responseTime="4696" source="7" lmin="64">
            <path dest="5" path="12,3,17" source="7"/>
            <path dest="8" path="12,13,20" source="7"/>
        </virtualLink>
        <virtualLink bag="128" dest="6,7" id="Designed for Data Flow 12" lmax="1278" number="12" responseTime="5112" source="5" lmin="64">
            <path dest="6" path="4,5,18" source="5"/>
            <path dest="7" path="4,5,9,19" source="5"/>
        </virtualLink>
        <virtualLink bag="128" dest="7" id="Designed for Data Flow 13" lmax="1125" number="13" responseTime="4152" source="8" lmin="64">
            <path dest="7" path="16,10,19" source="8"/>
        </virtualLink>
        <virtualLink bag="8" dest="5,6" id="Designed for Data Flow 14" lmax="745" number="14" responseTime="5206" source="8" lmin="64">
            <path dest="5" path="16,10,3,17" source="8"/>
            <path dest="6" path="16,7,18" source="8"/>
        </virtualLink>
        <virtualLink bag="16" dest="6" id="Designed for Data Flow 15" lmax="1225" number="15" responseTime="5113" source="5" lmin="64">
            <path dest="6" path="4,5,18" source="5"/>
        </virtualLink>
        <virtualLink bag="128" dest="6,8" id="Designed for Data Flow 16" lmax="621" number="16" responseTime="4982" source="7" lmin="64">
            <path dest="6" path="12,6,18" source="7"/>
            <path dest="8" path="12,13,20" source="7"/>
        </virtualLink>
        <virtualLink bag="128" dest="5" id="Designed for Data Flow 17" lmax="810" number="17" responseTime="4695" source="7" lmin="64">
            <path dest="5" path="12,3,17" source="7"/>
        </virtualLink>
        <virtualLink bag="128" dest="5,7,8" id="Designed for Data Flow 18" lmax="97" number="18" responseTime="3886" source="6" lmin="64">
            <path dest="5" path="8,1,17" source="6"/>
            <path dest="7" path="8,9,19" source="6"/>
            <path dest="8" path="8,15,20" source="6"/>
        </virtualLink>
        <virtualLink bag="64" dest="5,6,8" id="Designed for Data Flow 19" lmax="958" number="19" responseTime="4982" source="7" lmin="64">
            <path dest="5" path="12,3,17" source="7"/>
            <path dest="6" path="12,6,18" source="7"/>
            <path dest="8" path="12,13,20" source="7"/>
        </virtualLink>
        <virtualLink bag="8" dest="6,8" id="Designed for Data Flow 20" lmax="1221" number="20" responseTime="5236" source="5" lmin="64">
            <path dest="6" path="4,5,18" source="5"/>
            <path dest="8" path="4,5,15,20" source="5"/>
        </virtualLink>
        <virtualLink bag="128" dest="8" id="Designed for Data Flow 21" lmax="1307" number="21" responseTime="4564" source="7" lmin="64">
            <path dest="8" path="12,13,20" source="7"/>
        </virtualLink>
        <virtualLink bag="64" dest="6,8" id="Designed for Data Flow 22" lmax="1331" number="22" responseTime="5107" source="7" lmin="64">
            <path dest="6" path="12,6,18" source="7"/>
            <path dest="8" path="12,6,15,20" source="7"/>
        </virtualLink>
        <virtualLink bag="128" dest="5,7" id="Designed for Data Flow 23" lmax="761" number="23" responseTime="4612" source="8" lmin="64">
            <path dest="5" path="16,2,17" source="8"/>
            <path dest="7" path="16,10,19" source="8"/>
        </virtualLink>
        <virtualLink bag="128" dest="5,7,8" id="Designed for Data Flow 24" lmax="845" number="24" responseTime="3886" source="6" lmin="64">
            <path dest="5" path="8,1,17" source="6"/>
            <path dest="7" path="8,9,19" source="6"/>
            <path dest="8" path="8,15,20" source="6"/>
        </virtualLink>
        <virtualLink bag="64" dest="8" id="Designed for Data Flow 25" lmax="1205" number="25" responseTime="4337" source="5" lmin="64">
            <path dest="8" path="4,14,20" source="5"/>
        </virtualLink>
        <virtualLink bag="128" dest="5,8" id="Designed for Data Flow 26" lmax="614" number="26" responseTime="4695" source="7" lmin="64">
            <path dest="5" path="12,3,17" source="7"/>
            <path dest="8" path="12,13,20" source="7"/>
        </virtualLink>
        <virtualLink bag="128" dest="6" id="Designed for Data Flow 27" lmax="864" number="27" responseTime="5207" source="8" lmin="64">
            <path dest="6" path="16,7,18" source="8"/>
        </virtualLink>
        <virtualLink bag="16" dest="5,8" id="Designed for Data Flow 28" lmax="991" number="28" responseTime="4695" source="7" lmin="64">
            <path dest="5" path="12,3,17" source="7"/>
            <path dest="8" path="12,13,20" source="7"/>
        </virtualLink>
        <virtualLink bag="2" dest="5,6,8" id="Designed for Data Flow 29" lmax="1078" number="29" responseTime="4983" source="7" lmin="64">
            <path dest="6" path="12,6,18" source="7"/>
        </virtualLink>
        <virtualLink bag="64" dest="6" id="Designed for Data Flow 30" lmax="1132" number="30" responseTime="5206" source="8" lmin="64">
            <path dest="6" path="16,7,18" source="8"/>
        </virtualLink>
        <virtualLink bag="64" dest="5,6,7" id="Designed for Data Flow 31" lmax="958" number="31" responseTime="5206" source="8" lmin="64">
            <path dest="5" path="16,2,17" source="8"/>
            <path dest="6" path="16,7,18" source="8"/>
            <path dest="7" path="16,10,19" source="8"/>
        </virtualLink>
        <virtualLink bag="64" dest="7" id="Designed for Data Flow 32" lmax="945" number="32" responseTime="4162" source="5" lmin="64">
            <path dest="7" path="4,11,19" source="5"/>
        </virtualLink>
        <virtualLink bag="128" dest="5,6,7" id="Designed for Data Flow 33" lmax="1437" number="33" responseTime="5206" source="8" lmin="64">
            <path dest="5" path="16,2,17" source="8"/>
            <path dest="6" path="16,7,18" source="8"/>
            <path dest="7" path="16,10,19" source="8"/>
        </virtualLink>
        <virtualLink bag="8" dest="6,7,8" id="Designed for Data Flow 34" lmax="833" number="34" responseTime="5236" source="5" lmin="64">
            <path dest="6" path="4,5,18" source="5"/>
            <path dest="7" path="4,5,9,19" source="5"/>
            <path dest="8" path="4,5,15,20" source="5"/>
        </virtualLink>
        <virtualLink bag="32" dest="5,6,7" id="Designed for Data Flow 35" lmax="812" number="35" responseTime="5206" source="8" lmin="64">
            <path dest="5" path="16,2,17" source="8"/>
            <path dest="6" path="16,7,18" source="8"/>
            <path dest="7" path="16,10,19" source="8"/>
        </virtualLink>
        <virtualLink bag="128" dest="6,8" id="Designed for Data Flow 36" lmax="1174" number="36" responseTime="5107" source="7" lmin="64">
            <path dest="6" path="12,6,18" source="7"/>
            <path dest="8" path="12,6,15,20" source="7"/>
        </virtualLink>
        <virtualLink bag="64" dest="6,7" id="Designed for Data Flow 37" lmax="714" number="37" responseTime="5207" source="8" lmin="64">
            <path dest="6" path="16,7,18" source="8"/>
            <path dest="7" path="16,10,19" source="8"/>
        </virtualLink>
        <virtualLink bag="64" dest="6,7" id="Designed for Data Flow 38" lmax="68" number="38" responseTime="5207" source="8" lmin="64">
            <path dest="6" path="16,7,18" source="8"/>
            <path dest="7" path="16,10,19" source="8"/>
        </virtualLink>
        <virtualLink bag="32" dest="5,6,8" id="Designed for Data Flow 39" lmax="789" number="39" responseTime="5107" source="7" lmin="64">
            <path dest="5" path="12,3,17" source="7"/>
            <path dest="6" path="12,6,18" source="7"/>
            <path dest="8" path="12,6,15,20" source="7"/>
        </virtualLink>
        <virtualLink bag="32" dest="5,7,8" id="Designed for Data Flow 40" lmax="948" number="40" responseTime="3886" source="6" lmin="64">
            <path dest="5" path="8,1,17" source="6"/>
            <path dest="7" path="8,9,19" source="6"/>
            <path dest="8" path="8,15,20" source="6"/>
        </virtualLink>
        <virtualLink bag="32" dest="6" id="Designed for Data Flow 41" lmax="1170" number="41" responseTime="5457" source="5" lmin="64">
            <path dest="6" path="4,14,7,18" source="5"/>
        </virtualLink>
        <virtualLink bag="32" dest="5,6" id="Designed for Data Flow 42" lmax="902" number="42" responseTime="4983" source="7" lmin="64">
            <path dest="5" path="12,3,17" source="7"/>
            <path dest="6" path="12,6,18" source="7"/>
        </virtualLink>
        <virtualLink bag="128" dest="6,7,8" id="Designed for Data Flow 43" lmax="235" number="43" responseTime="5237" source="5" lmin="64">
            <path dest="6" path="4,5,18" source="5"/>
            <path dest="7" path="4,5,9,19" source="5"/>
            <path dest="8" path="4,5,15,20" source="5"/>
        </virtualLink>
        <virtualLink bag="128" dest="5,7,8" id="Designed for Data Flow 44" lmax="540" number="44" responseTime="3886" source="6" lmin="64">
            <path dest="5" path="8,1,17" source="6"/>
            <path dest="7" path="8,9,19" source="6"/>
            <path dest="8" path="8,15,20" source="6"/>
        </virtualLink>
        <virtualLink bag="128" dest="5,6,8" id="Designed for Data Flow 45" lmax="1328" number="45" responseTime="4983" source="7" lmin="64">
            <path dest="5" path="12,3,17" source="7"/>
            <path dest="6" path="12,6,18" source="7"/>
            <path dest="8" path="12,13,20" source="7"/>
        </virtualLink>
        <virtualLink bag="128" dest="6,8" id="Designed for Data Flow 46" lmax="642" number="46" responseTime="5236" source="5" lmin="64">
            <path dest="6" path="4,5,18" source="5"/>
            <path dest="8" path="4,5,15,20" source="5"/>
        </virtualLink>
        <virtualLink bag="128" dest="6" id="Designed for Data Flow 47" lmax="690" number="47" responseTime="4983" source="7" lmin="64">
            <path dest="6" path="12,6,18" source="7"/>
        </virtualLink>
        <virtualLink bag="128" dest="6" id="Designed for Data Flow 48" lmax="432" number="48" responseTime="4983" source="7" lmin="64">
            <path dest="6" path="12,6,18" source="7"/>
        </virtualLink>
        <virtualLink bag="8" dest="6,7,8" id="Designed for Data Flow 49" lmax="1209" number="49" responseTime="5236" source="5" lmin="64">
            <path dest="6" path="4,5,18" source="5"/>
            <path dest="7" path="4,5,9,19" source="5"/>
            <path dest="8" path="4,5,15,20" source="5"/>
        </virtualLink>
        <virtualLink bag="128" dest="8" id="Designed for Data Flow 50" lmax="1170" number="50" responseTime="4337" source="5" lmin="64">
            <path dest="8" path="4,14,20" source="5"/>
        </virtualLink>
        <virtualLink bag="64" dest="5,6" id="Designed for Data Flow 51" lmax="1433" number="51" responseTime="5206" source="8" lmin="64">
            <path dest="5" path="16,2,17" source="8"/>
            <path dest="6" path="16,7,18" source="8"/>
        </virtualLink>
        <virtualLink bag="128" dest="5" id="Designed for Data Flow 52" lmax="696" number="52" responseTime="4612" source="8" lmin="64">
            <path dest="5" path="16,2,17" source="8"/>
        </virtualLink>
        <virtualLink bag="64" dest="5,6" id="Designed for Data Flow 53" lmax="778" number="53" responseTime="5207" source="8" lmin="64">
            <path dest="5" path="16,2,17" source="8"/>
            <path dest="6" path="16,7,18" source="8"/>
        </virtualLink>
        <virtualLink bag="32" dest="5,7,8" id="Designed for Data Flow 54" lmax="671" number="54" responseTime="4276" source="6" lmin="64">
            <path dest="5" path="8,1,17" source="6"/>
            <path dest="7" path="8,9,19" source="6"/>
            <path dest="8" path="8,9,13,20" source="6"/>
        </virtualLink>
        <virtualLink bag="8" dest="7,8" id="Designed for Data Flow 55" lmax="1218" number="55" responseTime="4758" source="5" lmin="64">
            <path dest="7" path="4,11,19" source="5"/>
            <path dest="8" path="4,11,13,20" source="5"/>
        </virtualLink>
        <virtualLink bag="64" dest="8" id="Designed for Data Flow 56" lmax="663" number="56" responseTime="4564" source="7" lmin="64">
            <path dest="8" path="12,13,20" source="7"/>
        </virtualLink>
        <virtualLink bag="64" dest="5,6" id="Designed for Data Flow 57" lmax="680" number="57" responseTime="4983" source="7" lmin="64">
            <path dest="5" path="12,3,17" source="7"/>
            <path dest="6" path="12,6,18" source="7"/>
        </virtualLink>
        <virtualLink bag="128" dest="7" id="Designed for Data Flow 58" lmax="513" number="58" responseTime="3681" source="6" lmin="64">
            <path dest="7" path="8,9,19" source="6"/>
        </virtualLink>
        <virtualLink bag="128" dest="6" id="Designed for Data Flow 59" lmax="1194" number="59" responseTime="4983" source="7" lmin="64">
            <path dest="6" path="12,6,18" source="7"/>
        </virtualLink>
        <virtualLink bag="128" dest="5" id="Designed for Data Flow 60" lmax="1367" number="60" responseTime="4613" source="8" lmin="64">
            <path dest="5" path="16,2,17" source="8"/>
        </virtualLink>
        <virtualLink bag="128" dest="5" id="Designed for Data Flow 61" lmax="1006" number="61" responseTime="4696" source="7" lmin="64">
            <path dest="5" path="12,3,17" source="7"/>
        </virtualLink>
        <virtualLink bag="64" dest="8" id="Designed for Data Flow 62" lmax="985" number="62" responseTime="3886" source="6" lmin="64">
            <path dest="8" path="8,15,20" source="6"/>
        </virtualLink>
        <virtualLink bag="128" dest="5,6,8" id="Designed for Data Flow 63" lmax="1034" number="63" responseTime="5106" source="7" lmin="64">
            <path dest="5" path="12,3,17" source="7"/>
            <path dest="6" path="12,6,18" source="7"/>
            <path dest="8" path="12,6,15,20" source="7"/>
        </virtualLink>
        <virtualLink bag="64" dest="5,6,7" id="Designed for Data Flow 64" lmax="1298" number="64" responseTime="5206" source="8" lmin="64">
            <path dest="5" path="16,2,17" source="8"/>
            <path dest="6" path="16,7,18" source="8"/>
            <path dest="7" path="16,10,19" source="8"/>
        </virtualLink>
        <virtualLink bag="128" dest="5,6,7" id="Designed for Data Flow 65" lmax="311" number="65" responseTime="5206" source="8" lmin="64">
            <path dest="5" path="16,2,17" source="8"/>
            <path dest="6" path="16,7,18" source="8"/>
            <path dest="7" path="16,10,19" source="8"/>
        </virtualLink>
        <virtualLink bag="32" dest="6,7,8" id="Designed for Data Flow 66" lmax="974" number="66" responseTime="5237" source="5" lmin="64">
            <path dest="6" path="4,5,18" source="5"/>
            <path dest="7" path="4,5,9,19" source="5"/>
            <path dest="8" path="4,5,15,20" source="5"/>
        </virtualLink>
        <virtualLink bag="128" dest="7" id="Designed for Data Flow 67" lmax="878" number="67" responseTime="4162" source="5" lmin="64">
            <path dest="7" path="4,11,19" source="5"/>
        </virtualLink>
        <virtualLink bag="64" dest="7,8" id="Designed for Data Flow 68" lmax="718" number="68" responseTime="4276" source="6" lmin="64">
            <path dest="7" path="8,9,19" source="6"/>
            <path dest="8" path="8,9,13,20" source="6"/>
        </virtualLink>
        <virtualLink bag="128" dest="5" id="Designed for Data Flow 69" lmax="654" number="69" responseTime="3684" source="6" lmin="64">
            <path dest="5" path="8,1,17" source="6"/>
        </virtualLink>
        <virtualLink bag="128" dest="6,7,8" id="Designed for Data Flow 70" lmax="839" number="70" responseTime="5236" source="5" lmin="64">
            <path dest="6" path="4,5,18" source="5"/>
            <path dest="7" path="4,5,9,19" source="5"/>
            <path dest="8" path="4,5,15,20" source="5"/>
        </virtualLink>
        <virtualLink bag="64" dest="5" id="Designed for Data Flow 71" lmax="814" number="71" responseTime="4695" source="7" lmin="64">
            <path dest="5" path="12,3,17" source="7"/>
        </virtualLink>
        <virtualLink bag="128" dest="6,8" id="Designed for Data Flow 72" lmax="107" number="72" responseTime="4983" source="7" lmin="64">
            <path dest="6" path="12,6,18" source="7"/>
            <path dest="8" path="12,13,20" source="7"/>
        </virtualLink>
        <virtualLink bag="128" dest="6,7,8" id="Designed for Data Flow 73" lmax="1340" number="73" responseTime="5236" source="5" lmin="64">
            <path dest="6" path="4,5,18" source="5"/>
            <path dest="7" path="4,5,9,19" source="5"/>
            <path dest="8" path="4,5,15,20" source="5"/>
        </virtualLink>
        <virtualLink bag="32" dest="6,7,8" id="Designed for Data Flow 74" lmax="1023" number="74" responseTime="5457" source="5" lmin="64">
            <path dest="6" path="4,14,7,18" source="5"/>
            <path dest="7" path="4,14,10,19" source="5"/>
            <path dest="8" path="4,14,20" source="5"/>
        </virtualLink>
        <virtualLink bag="128" dest="5,7" id="Designed for Data Flow 75" lmax="851" number="75" responseTime="3684" source="6" lmin="64">
            <path dest="5" path="8,1,17" source="6"/>
            <path dest="7" path="8,9,19" source="6"/>
        </virtualLink>
        <virtualLink bag="128" dest="6,7,8" id="Designed for Data Flow 76" lmax="1325" number="76" responseTime="5237" source="5" lmin="64">
            <path dest="6" path="4,5,18" source="5"/>
            <path dest="7" path="4,5,9,19" source="5"/>
            <path dest="8" path="4,5,15,20" source="5"/>
        </virtualLink>
        <virtualLink bag="64" dest="6" id="Designed for Data Flow 77" lmax="855" number="77" responseTime="5112" source="5" lmin="64">
            <path dest="6" path="4,5,18" source="5"/>
        </virtualLink>
        <virtualLink bag="128" dest="5,6,7" id="Designed for Data Flow 78" lmax="1248" number="78" responseTime="5206" source="8" lmin="64">
            <path dest="5" path="16,2,17" source="8"/>
            <path dest="6" path="16,7,18" source="8"/>
            <path dest="7" path="16,10,19" source="8"/>
        </virtualLink>
        <virtualLink bag="16" dest="5,6,8" id="Designed for Data Flow 79" lmax="829" number="79" responseTime="4983" source="7" lmin="64">
            <path dest="5" path="12,3,17" source="7"/>
            <path dest="6" path="12,6,18" source="7"/>
            <path dest="8" path="12,13,20" source="7"/>
        </virtualLink>
        <virtualLink bag="8" dest="5,8" id="Designed for Data Flow 80" lmax="823" number="80" responseTime="3886" source="6" lmin="64">
            <path dest="5" path="8,1,17" source="6"/>
            <path dest="8" path="8,15,20" source="6"/>
        </virtualLink>
        <virtualLink bag="128" dest="5,6,7" id="Designed for Data Flow 81" lmax="380" number="81" responseTime="5207" source="8" lmin="64">
            <path dest="5" path="16,2,17" source="8"/>
            <path dest="6" path="16,7,18" source="8"/>
            <path dest="7" path="16,10,19" source="8"/>
        </virtualLink>
        <virtualLink bag="8" dest="5,6" id="Designed for Data Flow 82" lmax="944" number="82" responseTime="5206" source="8" lmin="64">
            <path dest="5" path="16,7,1,17" source="8"/>
            <path dest="6" path="16,7,18" source="8"/>
        </virtualLink>
        <virtualLink bag="32" dest="8" id="Designed for Data Flow 83" lmax="1313" number="83" responseTime="4338" source="5" lmin="64">
            <path dest="8" path="4,14,20" source="5"/>
        </virtualLink>
        <virtualLink bag="64" dest="7" id="Designed for Data Flow 84" lmax="1014" number="84" responseTime="4152" source="8" lmin="64">
            <path dest="7" path="16,10,19" source="8"/>
        </virtualLink>
        <virtualLink bag="128" dest="6,7,8" id="Designed for Data Flow 85" lmax="66" number="85" responseTime="5626" source="5" lmin="64">
            <path dest="6" path="4,5,18" source="5"/>
            <path dest="7" path="4,5,9,19" source="5"/>
            <path dest="8" path="4,5,9,13,20" source="5"/>
        </virtualLink>
        <virtualLink bag="32" dest="8" id="Designed for Data Flow 86" lmax="921" number="86" responseTime="4337" source="5" lmin="64">
            <path dest="8" path="4,14,20" source="5"/>
        </virtualLink>
        <virtualLink bag="64" dest="5,7" id="Designed for Data Flow 87" lmax="469" number="87" responseTime="3685" source="6" lmin="64">
            <path dest="5" path="8,1,17" source="6"/>
            <path dest="7" path="8,9,19" source="6"/>
        </virtualLink>
        <virtualLink bag="128" dest="5,6,7" id="Designed for Data Flow 88" lmax="856" number="88" responseTime="5206" source="8" lmin="64">
            <path dest="5" path="16,2,17" source="8"/>
            <path dest="6" path="16,7,18" source="8"/>
            <path dest="7" path="16,10,19" source="8"/>
        </virtualLink>
        <virtualLink bag="128" dest="5" id="Designed for Data Flow 89" lmax="1031" number="89" responseTime="4612" source="8" lmin="64">
            <path dest="5" path="16,2,17" source="8"/>
        </virtualLink>
        <virtualLink bag="32" dest="6,7" id="Designed for Data Flow 90" lmax="796" number="90" responseTime="5206" source="8" lmin="64">
            <path dest="6" path="16,7,18" source="8"/>
            <path dest="7" path="16,10,19" source="8"/>
        </virtualLink>
        <virtualLink bag="128" dest="5" id="Designed for Data Flow 91" lmax="434" number="91" responseTime="3685" source="6" lmin="64">
            <path dest="5" path="8,1,17" source="6"/>
        </virtualLink>
        <virtualLink bag="128" dest="7" id="Designed for Data Flow 92" lmax="560" number="92" responseTime="4152" source="8" lmin="64">
            <path dest="7" path="16,10,19" source="8"/>
        </virtualLink>
        <virtualLink bag="128" dest="5,7" id="Designed for Data Flow 93" lmax="878" number="93" responseTime="3684" source="6" lmin="64">
            <path dest="5" path="8,1,17" source="6"/>
            <path dest="7" path="8,9,19" source="6"/>
        </virtualLink>
        <virtualLink bag="128" dest="5,7" id="Designed for Data Flow 94" lmax="1063" number="94" responseTime="4612" source="8" lmin="64">
            <path dest="5" path="16,2,17" source="8"/>
            <path dest="7" path="16,10,19" source="8"/>
        </virtualLink>
        <virtualLink bag="128" dest="6,7" id="Designed for Data Flow 95" lmax="435" number="95" responseTime="5113" source="5" lmin="64">
            <path dest="6" path="4,5,18" source="5"/>
            <path dest="7" path="4,5,9,19" source="5"/>
        </virtualLink>
        <virtualLink bag="64" dest="5,7" id="Designed for Data Flow 96" lmax="1333" number="96" responseTime="3685" source="6" lmin="64">
            <path dest="5" path="8,1,17" source="6"/>
            <path dest="7" path="8,9,19" source="6"/>
        </virtualLink>
        <virtualLink bag="32" dest="8" id="Designed for Data Flow 97" lmax="1389" number="97" responseTime="4564" source="7" lmin="64">
            <path dest="8" path="12,13,20" source="7"/>
        </virtualLink>
        <virtualLink bag="128" dest="7" id="Designed for Data Flow 98" lmax="787" number="98" responseTime="4162" source="5" lmin="64">
            <path dest="7" path="4,11,19" source="5"/>
        </virtualLink>
        <virtualLink bag="128" dest="7" id="Designed for Data Flow 99" lmax="1399" number="99" responseTime="4152" source="8" lmin="64">
            <path dest="7" path="16,10,19" source="8"/>
        </virtualLink>
        <virtualLink bag="1" dest="5,6,7" id="Designed for Data Flow 100" lmax="638" number="100" responseTime="5287" source="8" lmin="64">
            <path dest="5" path="16,2,17" source="8"/>
            <path dest="6" path="16,2,5,18" source="8"/>
            <path dest="7" path="16,2,11,19" source="8"/>
        </virtualLink>
    </virtualLinks>
    <dataFlows>
        <dataFlow dest="9,12" id="Data Flow 1" jMax="0" msgSize="2825" period="465" source="11" tMax="300" vl="1"/>
        <dataFlow dest="12" id="Data Flow 2" jMax="0" msgSize="1990" period="387" source="10" tMax="300" vl="2"/>
        <dataFlow dest="10" id="Data Flow 3" jMax="0" msgSize="3054" period="448" source="12" tMax="300" vl="3"/>
        <dataFlow dest="10,11,12" id="Data Flow 4" jMax="0" msgSize="1788" period="412" source="9" tMax="300" vl="4"/>
        <dataFlow dest="12,10" id="Data Flow 5" jMax="0" msgSize="712" period="434" source="11" tMax="300" vl="5"/>
        <dataFlow dest="9,10" id="Data Flow 6" jMax="0" msgSize="2549" period="14" source="11" tMax="300" vl="6"/>
        <dataFlow dest="12,10" id="Data Flow 7" jMax="0" msgSize="551" period="473" source="9" tMax="300" vl="7"/>
        <dataFlow dest="9,12,11" id="Data Flow 8" jMax="0" msgSize="1938" period="57" source="10" tMax="300" vl="8"/>
        <dataFlow dest="10,9" id="Data Flow 9" jMax="0" msgSize="1320" period="371" source="11" tMax="300" vl="9"/>
        <dataFlow dest="11,10" id="Data Flow 10" jMax="0" msgSize="1668" period="211" source="9" tMax="300" vl="10"/>
        <dataFlow dest="9,12" id="Data Flow 11" jMax="0" msgSize="3170" period="222" source="11" tMax="300" vl="11"/>
        <dataFlow dest="10,11" id="Data Flow 12" jMax="0" msgSize="3692" period="389" source="9" tMax="300" vl="12"/>
        <dataFlow dest="11" id="Data Flow 13" jMax="0" msgSize="2155" period="330" source="12" tMax="300" vl="13"/>
        <dataFlow dest="9,10" id="Data Flow 14" jMax="0" msgSize="3487" period="40" source="12" tMax="300" vl="14"/>
        <dataFlow dest="10" id="Data Flow 15" jMax="0" msgSize="2355" period="32" source="9" tMax="300" vl="15"/>
        <dataFlow dest="12,10" id="Data Flow 16" jMax="0" msgSize="1720" period="438" source="11" tMax="300" vl="16"/>
        <dataFlow dest="9" id="Data Flow 17" jMax="0" msgSize="2287" period="390" source="11" tMax="300" vl="17"/>
        <dataFlow dest="9,12,11" id="Data Flow 18" jMax="0" msgSize="50" period="215" source="10" tMax="300" vl="18"/>
        <dataFlow dest="10,9,12" id="Data Flow 19" jMax="0" msgSize="3642" period="299" source="11" tMax="300" vl="19"/>
        <dataFlow dest="12,10" id="Data Flow 20" jMax="0" msgSize="2347" period="20" source="9" tMax="300" vl="20"/>
        <dataFlow dest="12" id="Data Flow 21" jMax="0" msgSize="1260" period="379" source="11" tMax="300" vl="21"/>
        <dataFlow dest="12,10" id="Data Flow 22" jMax="0" msgSize="2568" period="145" source="11" tMax="300" vl="22"/>
        <dataFlow dest="11,9" id="Data Flow 23" jMax="0" msgSize="2141" period="481" source="12" tMax="300" vl="23"/>
        <dataFlow dest="9,12,11" id="Data Flow 24" jMax="0" msgSize="2392" period="483" source="10" tMax="300" vl="24"/>
        <dataFlow dest="12" id="Data Flow 25" jMax="0" msgSize="3473" period="199" source="9" tMax="300" vl="25"/>
        <dataFlow dest="12,9" id="Data Flow 26" jMax="0" msgSize="567" period="209" source="11" tMax="300" vl="26"/>
        <dataFlow dest="10" id="Data Flow 27" jMax="0" msgSize="2449" period="485" source="12" tMax="300" vl="27"/>
        <dataFlow dest="9,12" id="Data Flow 28" jMax="0" msgSize="2830" period="58" source="11" tMax="300" vl="28"/>
        <dataFlow dest="12,9,10" id="Data Flow 29" jMax="0" msgSize="2061" period="5" source="11" tMax="300" vl="29"/>
        <dataFlow dest="10" id="Data Flow 30" jMax="0" msgSize="2170" period="131" source="12" tMax="300" vl="30"/>
        <dataFlow dest="11,9,10" id="Data Flow 31" jMax="0" msgSize="1822" period="136" source="12" tMax="300" vl="31"/>
        <dataFlow dest="11" id="Data Flow 32" jMax="0" msgSize="2694" period="207" source="9" tMax="300" vl="32"/>
        <dataFlow dest="10,11,9" id="Data Flow 33" jMax="0" msgSize="1390" period="486" source="12" tMax="300" vl="33"/>
        <dataFlow dest="10,11,12" id="Data Flow 34" jMax="0" msgSize="3141" period="36" source="9" tMax="300" vl="34"/>
        <dataFlow dest="11,9,10" id="Data Flow 35" jMax="0" msgSize="3822" period="164" source="12" tMax="300" vl="35"/>
        <dataFlow dest="10,12" id="Data Flow 36" jMax="0" msgSize="3380" period="477" source="11" tMax="300" vl="36"/>
        <dataFlow dest="11,10" id="Data Flow 37" jMax="0" msgSize="3333" period="356" source="12" tMax="300" vl="37"/>
        <dataFlow dest="11,10" id="Data Flow 38" jMax="0" msgSize="21" period="111" source="12" tMax="300" vl="38"/>
        <dataFlow dest="12,9,10" id="Data Flow 39" jMax="0" msgSize="2968" period="137" source="11" tMax="300" vl="39"/>
        <dataFlow dest="9,11,12" id="Data Flow 40" jMax="0" msgSize="3601" period="131" source="10" tMax="300" vl="40"/>
        <dataFlow dest="10" id="Data Flow 41" jMax="0" msgSize="1123" period="48" source="9" tMax="300" vl="41"/>
        <dataFlow dest="9,10" id="Data Flow 42" jMax="0" msgSize="855" period="36" source="11" tMax="300" vl="42"/>
        <dataFlow dest="10,12,11" id="Data Flow 43" jMax="0" msgSize="188" period="230" source="9" tMax="300" vl="43"/>
        <dataFlow dest="9,11,12" id="Data Flow 44" jMax="0" msgSize="493" period="228" source="10" tMax="300" vl="44"/>
        <dataFlow dest="9,12,10" id="Data Flow 45" jMax="0" msgSize="1281" period="468" source="11" tMax="300" vl="45"/>
        <dataFlow dest="10,12" id="Data Flow 46" jMax="0" msgSize="1784" period="457" source="9" tMax="300" vl="46"/>
        <dataFlow dest="10" id="Data Flow 47" jMax="0" msgSize="1927" period="460" source="11" tMax="300" vl="47"/>
        <dataFlow dest="10" id="Data Flow 48" jMax="0" msgSize="385" period="156" source="11" tMax="300" vl="48"/>
        <dataFlow dest="11,10,12" id="Data Flow 49" jMax="0" msgSize="2323" period="19" source="9" tMax="300" vl="49"/>
        <dataFlow dest="12" id="Data Flow 50" jMax="0" msgSize="3367" period="499" source="9" tMax="300" vl="50"/>
        <dataFlow dest="10,9" id="Data Flow 51" jMax="0" msgSize="2771" period="169" source="12" tMax="300" vl="51"/>
        <dataFlow dest="9" id="Data Flow 52" jMax="0" msgSize="1947" period="500" source="12" tMax="300" vl="52"/>
        <dataFlow dest="9,10" id="Data Flow 53" jMax="0" msgSize="3653" period="363" source="12" tMax="300" vl="53"/>
        <dataFlow dest="9,11,12" id="Data Flow 54" jMax="0" msgSize="1872" period="122" source="10" tMax="300" vl="54"/>
        <dataFlow dest="11,12" id="Data Flow 55" jMax="0" msgSize="3512" period="28" source="9" tMax="300" vl="55"/>
        <dataFlow dest="12" id="Data Flow 56" jMax="0" msgSize="3080" period="383" source="11" tMax="300" vl="56"/>
        <dataFlow dest="10,9" id="Data Flow 57" jMax="0" msgSize="633" period="115" source="11" tMax="300" vl="57"/>
        <dataFlow dest="11" id="Data Flow 58" jMax="0" msgSize="466" period="130" source="10" tMax="300" vl="58"/>
        <dataFlow dest="10" id="Data Flow 59" jMax="0" msgSize="3440" period="462" source="11" tMax="300" vl="59"/>
        <dataFlow dest="9" id="Data Flow 60" jMax="0" msgSize="1320" period="408" source="12" tMax="300" vl="60"/>
        <dataFlow dest="9" id="Data Flow 61" jMax="0" msgSize="2877" period="404" source="11" tMax="300" vl="61"/>
        <dataFlow dest="12" id="Data Flow 62" jMax="0" msgSize="3750" period="260" source="10" tMax="300" vl="62"/>
        <dataFlow dest="10,12,9" id="Data Flow 63" jMax="0" msgSize="987" period="283" source="11" tMax="300" vl="63"/>
        <dataFlow dest="9,11,10" id="Data Flow 64" jMax="0" msgSize="2502" period="149" source="12" tMax="300" vl="64"/>
        <dataFlow dest="9,10,11" id="Data Flow 65" jMax="0" msgSize="264" period="144" source="12" tMax="300" vl="65"/>
        <dataFlow dest="12,10,11" id="Data Flow 66" jMax="0" msgSize="3708" period="158" source="9" tMax="300" vl="66"/>
        <dataFlow dest="11" id="Data Flow 67" jMax="0" msgSize="2492" period="439" source="9" tMax="300" vl="67"/>
        <dataFlow dest="12,11" id="Data Flow 68" jMax="0" msgSize="671" period="82" source="10" tMax="300" vl="68"/>
        <dataFlow dest="9" id="Data Flow 69" jMax="0" msgSize="607" period="298" source="10" tMax="300" vl="69"/>
        <dataFlow dest="11,12,10" id="Data Flow 70" jMax="0" msgSize="1583" period="269" source="9" tMax="300" vl="70"/>
        <dataFlow dest="9" id="Data Flow 71" jMax="0" msgSize="2299" period="240" source="11" tMax="300" vl="71"/>
        <dataFlow dest="12,10" id="Data Flow 72" jMax="0" msgSize="60" period="160" source="11" tMax="300" vl="72"/>
        <dataFlow dest="10,12,11" id="Data Flow 73" jMax="0" msgSize="1293" period="232" source="9" tMax="300" vl="73"/>
        <dataFlow dest="12,11,10" id="Data Flow 74" jMax="0" msgSize="1951" period="87" source="9" tMax="300" vl="74"/>
        <dataFlow dest="11,9" id="Data Flow 75" jMax="0" msgSize="2410" period="442" source="10" tMax="300" vl="75"/>
        <dataFlow dest="12,10,11" id="Data Flow 76" jMax="0" msgSize="1278" period="271" source="9" tMax="300" vl="76"/>
        <dataFlow dest="10" id="Data Flow 77" jMax="0" msgSize="1615" period="146" source="9" tMax="300" vl="77"/>
        <dataFlow dest="11,9,10" id="Data Flow 78" jMax="0" msgSize="3602" period="392" source="12" tMax="300" vl="78"/>
        <dataFlow dest="12,9,10" id="Data Flow 79" jMax="0" msgSize="3907" period="91" source="11" tMax="300" vl="79"/>
        <dataFlow dest="12,9" id="Data Flow 80" jMax="0" msgSize="3102" period="39" source="10" tMax="300" vl="80"/>
        <dataFlow dest="10,9,11" id="Data Flow 81" jMax="0" msgSize="333" period="264" source="12" tMax="300" vl="81"/>
        <dataFlow dest="10,9" id="Data Flow 82" jMax="0" msgSize="897" period="9" source="12" tMax="300" vl="82"/>
        <dataFlow dest="12" id="Data Flow 83" jMax="0" msgSize="3798" period="106" source="9" tMax="300" vl="83"/>
        <dataFlow dest="11" id="Data Flow 84" jMax="0" msgSize="2899" period="246" source="12" tMax="300" vl="84"/>
        <dataFlow dest="11,10,12" id="Data Flow 85" jMax="0" msgSize="19" period="180" source="9" tMax="300" vl="85"/>
        <dataFlow dest="12" id="Data Flow 86" jMax="0" msgSize="3495" period="131" source="9" tMax="300" vl="86"/>
        <dataFlow dest="11,9" id="Data Flow 87" jMax="0" msgSize="422" period="114" source="10" tMax="300" vl="87"/>
        <dataFlow dest="11,10,9" id="Data Flow 88" jMax="0" msgSize="809" period="231" source="12" tMax="300" vl="88"/>
        <dataFlow dest="9" id="Data Flow 89" jMax="0" msgSize="984" period="443" source="12" tMax="300" vl="89"/>
        <dataFlow dest="10,11" id="Data Flow 90" jMax="0" msgSize="3744" period="163" source="12" tMax="300" vl="90"/>
        <dataFlow dest="9" id="Data Flow 91" jMax="0" msgSize="387" period="460" source="10" tMax="300" vl="91"/>
        <dataFlow dest="11" id="Data Flow 92" jMax="0" msgSize="1539" period="454" source="12" tMax="300" vl="92"/>
        <dataFlow dest="11,9" id="Data Flow 93" jMax="0" msgSize="831" period="159" source="10" tMax="300" vl="93"/>
        <dataFlow dest="9,11" id="Data Flow 94" jMax="0" msgSize="1016" period="215" source="12" tMax="300" vl="94"/>
        <dataFlow dest="10,11" id="Data Flow 95" jMax="0" msgSize="388" period="192" source="9" tMax="300" vl="95"/>
        <dataFlow dest="9,11" id="Data Flow 96" jMax="0" msgSize="2572" period="183" source="10" tMax="300" vl="96"/>
        <dataFlow dest="12" id="Data Flow 97" jMax="0" msgSize="2683" period="87" source="11" tMax="300" vl="97"/>
        <dataFlow dest="11" id="Data Flow 98" jMax="0" msgSize="1479" period="260" source="9" tMax="300" vl="98"/>
        <dataFlow dest="11" id="Data Flow 99" jMax="0" msgSize="2703" period="352" source="12" tMax="300" vl="99"/>
        <dataFlow dest="9,10,11" id="Data Flow 100" jMax="0" msgSize="2955" period="5" source="12" tMax="300" vl="100"/>
    </dataFlows>
</afdxxml>
