<afdxxml name="test project">
    <resources>
        <switch name="switch1" number="1" ports="1,2,3,4" x="231.5" y="209.5"/>
        <switch name="switch2" number="2" ports="5,6,7,8" x="380.5" y="206.5"/>
        <switch name="switch3" number="3" ports="9,10,11,12" x="380.5" y="332.5"/>
        <switch name="switch4" number="4" ports="13,14,15,16" x="223.5" y="333.5"/>
        <switch name="switch5" number="5" ports="17,18,19" x="301.5" y="149.5"/>
        <switch name="switch6" number="6" ports="20,21,22" x="448.5" y="269.5"/>
        <switch name="switch7" number="7" ports="23,24,25" x="296.5" y="395.5"/>
        <switch name="switch8" number="8" ports="26,27,28" x="154.5" y="273.5"/>
        <endSystem name="endSystem1" number="9" ports="29" x="301.5" y="79.5"/>
        <endSystem name="endSystem2" number="10" ports="30" x="530.5" y="266.5"/>
        <endSystem name="endSystem3" number="11" ports="31" x="296.5" y="470.5"/>
        <endSystem name="endSystem4" number="12" ports="32" x="67.5" y="271.5"/>
        <partition connectedTo="9" name="partition1" number="13" x="298.5" y="26.5"/>
        <partition connectedTo="10" name="partition2" number="14" x="590.5" y="264.5"/>
        <partition connectedTo="11" name="partition3" number="15" x="297.5" y="536.5"/>
        <partition connectedTo="12" name="partition4" number="16" x="13.5" y="271.5"/>
        <link capacity="12500" from="1" fromType="0" to="5" toType="0"/>
        <link capacity="12500" from="6" fromType="0" to="9" toType="0"/>
        <link capacity="12500" from="10" fromType="0" to="13" toType="0"/>
        <link capacity="12500" from="14" fromType="0" to="2" toType="0"/>
        <link capacity="12500" from="3" fromType="0" to="17" toType="0"/>
        <link capacity="12500" from="18" fromType="0" to="7" toType="0"/>
        <link capacity="12500" from="8" fromType="0" to="20" toType="0"/>
        <link capacity="12500" from="21" fromType="0" to="11" toType="0"/>
        <link capacity="12500" from="12" fromType="0" to="23" toType="0"/>
        <link capacity="12500" from="24" fromType="0" to="15" toType="0"/>
        <link capacity="12500" from="16" fromType="0" to="26" toType="0"/>
        <link capacity="12500" from="27" fromType="0" to="4" toType="0"/>
        <link capacity="12500" from="19" fromType="0" to="29" toType="0"/>
        <link capacity="12500" from="22" fromType="0" to="30" toType="0"/>
        <link capacity="12500" from="25" fromType="0" to="31" toType="0"/>
        <link capacity="12500" from="28" fromType="0" to="32" toType="0"/>
    </resources>
    <virtualLinks>
        <virtualLink bag="128" dest="10" id="Designed for Data Flow 1" lmax="223" number="1" responseTime="5443" source="11" lmin="64">
            <path dest="10" path="25,12,21,30" source="11"/>
        </virtualLink>
        <virtualLink bag="32" dest="12" id="Designed for Data Flow 2" lmax="1398" number="2" responseTime="6311" source="9" lmin="64">
            <path dest="12" path="19,3,27,32" source="9"/>
        </virtualLink>
        <virtualLink bag="16" dest="11,12" id="Designed for Data Flow 3" lmax="903" number="3" responseTime="6311" source="9" lmin="64">
            <path dest="11" path="19,3,14,24,31" source="9"/>
            <path dest="12" path="19,3,27,32" source="9"/>
        </virtualLink>
        <virtualLink bag="16" dest="9,11,12" id="Designed for Data Flow 4" lmax="804" number="4" responseTime="6762" source="10" lmin="64">
            <path dest="9" path="22,8,18,29" source="10"/>
            <path dest="11" path="22,8,9,23,31" source="10"/>
            <path dest="12" path="22,8,1,27,32" source="10"/>
        </virtualLink>
        <virtualLink bag="32" dest="10,11,12" id="Designed for Data Flow 5" lmax="861" number="5" responseTime="6634" source="9" lmin="64">
            <path dest="10" path="19,7,20,30" source="9"/>
            <path dest="11" path="19,7,9,23,31" source="9"/>
            <path dest="12" path="19,3,27,32" source="9"/>
        </virtualLink>
        <virtualLink bag="128" dest="9,10" id="Designed for Data Flow 6" lmax="738" number="6" responseTime="5765" source="11" lmin="64">
            <path dest="9" path="25,12,6,18,29" source="11"/>
            <path dest="10" path="25,12,21,30" source="11"/>
        </virtualLink>
        <virtualLink bag="128" dest="9,11,12" id="Designed for Data Flow 7" lmax="479" number="7" responseTime="7498" source="10" lmin="64">
            <path dest="9" path="22,8,18,29" source="10"/>
            <path dest="11" path="22,8,9,23,31" source="10"/>
            <path dest="12" path="22,8,18,3,27,32" source="10"/>
        </virtualLink>
        <virtualLink bag="32" dest="12" id="Designed for Data Flow 8" lmax="855" number="8" responseTime="6311" source="9" lmin="64">
            <path dest="12" path="19,3,27,32" source="9"/>
        </virtualLink>
        <virtualLink bag="32" dest="12" id="Designed for Data Flow 9" lmax="1215" number="9" responseTime="6311" source="9" lmin="64">
            <path dest="12" path="19,3,27,32" source="9"/>
        </virtualLink>
        <virtualLink bag="32" dest="11" id="Designed for Data Flow 10" lmax="1251" number="10" responseTime="6272" source="10" lmin="64">
            <path dest="11" path="22,11,23,31" source="10"/>
        </virtualLink>
        <virtualLink bag="32" dest="9,12" id="Designed for Data Flow 11" lmax="1155" number="11" responseTime="7017" source="11" lmin="64">
            <path dest="9" path="25,12,6,18,29" source="11"/>
            <path dest="12" path="25,12,6,1,27,32" source="11"/>
        </virtualLink>
        <virtualLink bag="64" dest="9,10,11" id="Designed for Data Flow 12" lmax="783" number="12" responseTime="5766" source="12" lmin="64">
            <path dest="9" path="28,4,17,29" source="12"/>
            <path dest="10" path="28,4,5,20,30" source="12"/>
            <path dest="11" path="28,4,14,24,31" source="12"/>
        </virtualLink>
        <virtualLink bag="64" dest="10" id="Designed for Data Flow 13" lmax="847" number="13" responseTime="5443" source="11" lmin="64">
            <path dest="10" path="25,12,21,30" source="11"/>
        </virtualLink>
        <virtualLink bag="32" dest="9,10" id="Designed for Data Flow 14" lmax="1258" number="14" responseTime="5234" source="12" lmin="64">
            <path dest="9" path="28,4,17,29" source="12"/>
            <path dest="10" path="28,4,5,20,30" source="12"/>
        </virtualLink>
        <virtualLink bag="16" dest="9,10" id="Designed for Data Flow 15" lmax="927" number="15" responseTime="5233" source="12" lmin="64">
            <path dest="9" path="28,4,17,29" source="12"/>
            <path dest="10" path="28,4,5,20,30" source="12"/>
        </virtualLink>
        <virtualLink bag="32" dest="9,10" id="Designed for Data Flow 16" lmax="1112" number="16" responseTime="5234" source="12" lmin="64">
            <path dest="9" path="28,4,17,29" source="12"/>
            <path dest="10" path="28,4,5,20,30" source="12"/>
        </virtualLink>
        <virtualLink bag="32" dest="11" id="Designed for Data Flow 17" lmax="1284" number="17" responseTime="6244" source="9" lmin="64">
            <path dest="11" path="19,3,14,24,31" source="9"/>
        </virtualLink>
        <virtualLink bag="32" dest="9" id="Designed for Data Flow 18" lmax="1084" number="18" responseTime="5765" source="11" lmin="64">
            <path dest="9" path="25,12,6,18,29" source="11"/>
        </virtualLink>
        <virtualLink bag="64" dest="10,11" id="Designed for Data Flow 19" lmax="966" number="19" responseTime="7448" source="9" lmin="64">
            <path dest="10" path="19,7,20,30" source="9"/>
            <path dest="11" path="19,7,20,11,23,31" source="9"/>
        </virtualLink>
        <virtualLink bag="16" dest="9,10,11" id="Designed for Data Flow 20" lmax="1278" number="20" responseTime="5580" source="12" lmin="64">
            <path dest="9" path="28,4,5,18,29" source="12"/>
            <path dest="10" path="28,4,5,20,30" source="12"/>
            <path dest="11" path="28,16,24,31" source="12"/>
        </virtualLink>
        <virtualLink bag="32" dest="10" id="Designed for Data Flow 21" lmax="1198" number="21" responseTime="5778" source="12" lmin="64">
            <path dest="10" path="28,16,10,21,30" source="12"/>
        </virtualLink>
        <virtualLink bag="16" dest="11" id="Designed for Data Flow 22" lmax="1300" number="22" responseTime="6272" source="10" lmin="64">
            <path dest="11" path="22,11,23,31" source="10"/>
        </virtualLink>
        <virtualLink bag="16" dest="12" id="Designed for Data Flow 23" lmax="984" number="23" responseTime="6311" source="9" lmin="64">
            <path dest="12" path="19,3,27,32" source="9"/>
        </virtualLink>
        <virtualLink bag="32" dest="9,12" id="Designed for Data Flow 24" lmax="1223" number="24" responseTime="6399" source="11" lmin="64">
            <path dest="9" path="25,15,2,17,29" source="11"/>
            <path dest="12" path="25,15,26,32" source="11"/>
        </virtualLink>
        <virtualLink bag="16" dest="10,12" id="Designed for Data Flow 25" lmax="993" number="25" responseTime="7017" source="11" lmin="64">
            <path dest="10" path="25,12,21,30" source="11"/>
            <path dest="12" path="25,12,6,1,27,32" source="11"/>
        </virtualLink>
        <virtualLink bag="32" dest="10" id="Designed for Data Flow 26" lmax="1115" number="26" responseTime="5778" source="12" lmin="64">
            <path dest="10" path="28,16,10,21,30" source="12"/>
        </virtualLink>
        <virtualLink bag="32" dest="9,10,12" id="Designed for Data Flow 27" lmax="974" number="27" responseTime="6405" source="11" lmin="64">
            <path dest="9" path="25,15,2,17,29" source="11"/>
            <path dest="10" path="25,15,10,21,30" source="11"/>
            <path dest="12" path="25,15,2,27,32" source="11"/>
        </virtualLink>
        <virtualLink bag="16" dest="9" id="Designed for Data Flow 28" lmax="1032" number="28" responseTime="5510" source="10" lmin="64">
            <path dest="9" path="22,8,18,29" source="10"/>
        </virtualLink>
        <virtualLink bag="128" dest="9" id="Designed for Data Flow 29" lmax="773" number="29" responseTime="5765" source="11" lmin="64">
            <path dest="9" path="25,12,6,18,29" source="11"/>
        </virtualLink>
        <virtualLink bag="128" dest="9,11" id="Designed for Data Flow 30" lmax="1080" number="30" responseTime="6271" source="10" lmin="64">
            <path dest="9" path="22,8,18,29" source="10"/>
            <path dest="11" path="22,11,23,31" source="10"/>
        </virtualLink>
        <virtualLink bag="16" dest="11,12" id="Designed for Data Flow 31" lmax="845" number="31" responseTime="7363" source="10" lmin="64">
            <path dest="11" path="22,11,23,31" source="10"/>
            <path dest="12" path="22,11,13,26,32" source="10"/>
        </virtualLink>
        <virtualLink bag="16" dest="10,11,12" id="Designed for Data Flow 32" lmax="1484" number="32" responseTime="6867" source="9" lmin="64">
            <path dest="10" path="19,7,9,21,30" source="9"/>
            <path dest="11" path="19,7,9,23,31" source="9"/>
            <path dest="12" path="19,7,1,27,32" source="9"/>
        </virtualLink>
        <virtualLink bag="32" dest="9" id="Designed for Data Flow 33" lmax="932" number="33" responseTime="5053" source="12" lmin="64">
            <path dest="9" path="28,4,17,29" source="12"/>
        </virtualLink>
        <virtualLink bag="128" dest="11,12" id="Designed for Data Flow 34" lmax="597" number="34" responseTime="7363" source="10" lmin="64">
            <path dest="11" path="22,11,23,31" source="10"/>
            <path dest="12" path="22,11,13,26,32" source="10"/>
        </virtualLink>
        <virtualLink bag="16" dest="9,11,12" id="Designed for Data Flow 35" lmax="957" number="35" responseTime="6762" source="10" lmin="64">
            <path dest="9" path="22,8,18,29" source="10"/>
            <path dest="11" path="22,11,23,31" source="10"/>
            <path dest="12" path="22,8,1,27,32" source="10"/>
        </virtualLink>
        <virtualLink bag="128" dest="10,11,12" id="Designed for Data Flow 36" lmax="695" number="36" responseTime="6634" source="9" lmin="64">
            <path dest="10" path="19,7,20,30" source="9"/>
            <path dest="11" path="19,7,9,23,31" source="9"/>
            <path dest="12" path="19,3,27,32" source="9"/>
        </virtualLink>
        <virtualLink bag="32" dest="9,11" id="Designed for Data Flow 37" lmax="862" number="37" responseTime="5185" source="12" lmin="64">
            <path dest="9" path="28,4,17,29" source="12"/>
            <path dest="11" path="28,16,24,31" source="12"/>
        </virtualLink>
        <virtualLink bag="16" dest="9,11" id="Designed for Data Flow 38" lmax="1436" number="38" responseTime="5766" source="12" lmin="64">
            <path dest="9" path="28,4,17,29" source="12"/>
            <path dest="11" path="28,4,14,24,31" source="12"/>
        </virtualLink>
        <virtualLink bag="16" dest="10,12" id="Designed for Data Flow 39" lmax="923" number="39" responseTime="6967" source="11" lmin="64">
            <path dest="10" path="25,12,21,30" source="11"/>
            <path dest="12" path="25,12,13,26,32" source="11"/>
        </virtualLink>
        <virtualLink bag="32" dest="9,11" id="Designed for Data Flow 40" lmax="1118" number="40" responseTime="5185" source="12" lmin="64">
            <path dest="9" path="28,4,17,29" source="12"/>
            <path dest="11" path="28,16,24,31" source="12"/>
        </virtualLink>
        <virtualLink bag="16" dest="9,11" id="Designed for Data Flow 41" lmax="843" number="41" responseTime="5185" source="12" lmin="64">
            <path dest="9" path="28,4,17,29" source="12"/>
            <path dest="11" path="28,16,24,31" source="12"/>
        </virtualLink>
        <virtualLink bag="128" dest="10,11,12" id="Designed for Data Flow 42" lmax="675" number="42" responseTime="8541" source="9" lmin="64">
            <path dest="10" path="19,7,20,30" source="9"/>
            <path dest="11" path="19,7,20,11,23,31" source="9"/>
            <path dest="12" path="19,7,20,11,13,26,32" source="9"/>
        </virtualLink>
        <virtualLink bag="64" dest="9,10,11" id="Designed for Data Flow 43" lmax="1255" number="43" responseTime="5234" source="12" lmin="64">
            <path dest="9" path="28,4,17,29" source="12"/>
            <path dest="10" path="28,4,5,20,30" source="12"/>
            <path dest="11" path="28,16,24,31" source="12"/>
        </virtualLink>
        <virtualLink bag="32" dest="9,11" id="Designed for Data Flow 44" lmax="1013" number="44" responseTime="5766" source="12" lmin="64">
            <path dest="9" path="28,4,17,29" source="12"/>
            <path dest="11" path="28,4,14,24,31" source="12"/>
        </virtualLink>
        <virtualLink bag="16" dest="12" id="Designed for Data Flow 45" lmax="939" number="45" responseTime="7363" source="10" lmin="64">
            <path dest="12" path="22,11,13,26,32" source="10"/>
        </virtualLink>
        <virtualLink bag="8" dest="9" id="Designed for Data Flow 46" lmax="786" number="46" responseTime="5625" source="11" lmin="64">
            <path dest="9" path="25,15,2,17,29" source="11"/>
        </virtualLink>
        <virtualLink bag="128" dest="12" id="Designed for Data Flow 47" lmax="1294" number="47" responseTime="6398" source="11" lmin="64">
            <path dest="12" path="25,15,26,32" source="11"/>
        </virtualLink>
        <virtualLink bag="64" dest="12" id="Designed for Data Flow 48" lmax="1298" number="48" responseTime="6762" source="10" lmin="64">
            <path dest="12" path="22,8,1,27,32" source="10"/>
        </virtualLink>
        <virtualLink bag="32" dest="9,10,12" id="Designed for Data Flow 49" lmax="1385" number="49" responseTime="6399" source="11" lmin="64">
            <path dest="9" path="25,15,2,17,29" source="11"/>
            <path dest="10" path="25,15,10,21,30" source="11"/>
            <path dest="12" path="25,15,26,32" source="11"/>
        </virtualLink>
        <virtualLink bag="32" dest="11,12" id="Designed for Data Flow 50" lmax="1481" number="50" responseTime="7012" source="9" lmin="64">
            <path dest="11" path="19,3,14,24,31" source="9"/>
            <path dest="12" path="19,3,14,26,32" source="9"/>
        </virtualLink>
        <virtualLink bag="32" dest="10,11" id="Designed for Data Flow 51" lmax="960" number="51" responseTime="7449" source="9" lmin="64">
            <path dest="10" path="19,7,20,30" source="9"/>
            <path dest="11" path="19,7,20,11,23,31" source="9"/>
        </virtualLink>
        <virtualLink bag="16" dest="12" id="Designed for Data Flow 52" lmax="1008" number="52" responseTime="6398" source="11" lmin="64">
            <path dest="12" path="25,15,26,32" source="11"/>
        </virtualLink>
        <virtualLink bag="32" dest="9,11,12" id="Designed for Data Flow 53" lmax="900" number="53" responseTime="7621" source="10" lmin="64">
            <path dest="9" path="22,8,18,29" source="10"/>
            <path dest="11" path="22,8,9,23,31" source="10"/>
            <path dest="12" path="22,8,9,13,26,32" source="10"/>
        </virtualLink>
        <virtualLink bag="16" dest="9,10,12" id="Designed for Data Flow 54" lmax="1453" number="54" responseTime="7753" source="11" lmin="64">
            <path dest="9" path="25,12,6,18,29" source="11"/>
            <path dest="10" path="25,12,21,30" source="11"/>
            <path dest="12" path="25,12,6,18,3,27,32" source="11"/>
        </virtualLink>
        <virtualLink bag="16" dest="10,11,12" id="Designed for Data Flow 55" lmax="950" number="55" responseTime="6867" source="9" lmin="64">
            <path dest="10" path="19,7,20,30" source="9"/>
            <path dest="11" path="19,7,9,23,31" source="9"/>
            <path dest="12" path="19,7,1,27,32" source="9"/>
        </virtualLink>
        <virtualLink bag="64" dest="10,11" id="Designed for Data Flow 56" lmax="931" number="56" responseTime="5778" source="12" lmin="64">
            <path dest="10" path="28,16,10,21,30" source="12"/>
            <path dest="11" path="28,16,24,31" source="12"/>
        </virtualLink>
        <virtualLink bag="16" dest="9,11,12" id="Designed for Data Flow 57" lmax="797" number="57" responseTime="7499" source="10" lmin="64">
            <path dest="9" path="22,8,18,29" source="10"/>
            <path dest="11" path="22,8,9,23,31" source="10"/>
            <path dest="12" path="22,8,18,3,27,32" source="10"/>
        </virtualLink>
        <virtualLink bag="32" dest="10,12" id="Designed for Data Flow 58" lmax="1168" number="58" responseTime="6967" source="11" lmin="64">
            <path dest="10" path="25,12,21,30" source="11"/>
            <path dest="12" path="25,12,13,26,32" source="11"/>
        </virtualLink>
        <virtualLink bag="16" dest="9,11" id="Designed for Data Flow 59" lmax="925" number="59" responseTime="5185" source="12" lmin="64">
            <path dest="9" path="28,4,17,29" source="12"/>
            <path dest="11" path="28,16,24,31" source="12"/>
        </virtualLink>
        <virtualLink bag="64" dest="11,12" id="Designed for Data Flow 60" lmax="1410" number="60" responseTime="8448" source="10" lmin="64">
            <path dest="11" path="22,11,23,31" source="10"/>
            <path dest="12" path="22,11,23,15,26,32" source="10"/>
        </virtualLink>
        <virtualLink bag="64" dest="10,11,12" id="Designed for Data Flow 61" lmax="1153" number="61" responseTime="8811" source="9" lmin="64">
            <path dest="10" path="19,7,20,30" source="9"/>
            <path dest="11" path="19,7,9,23,31" source="9"/>
            <path dest="12" path="19,7,9,23,15,26,32" source="9"/>
        </virtualLink>
        <virtualLink bag="32" dest="10,11,12" id="Designed for Data Flow 62" lmax="1418" number="62" responseTime="7449" source="9" lmin="64">
            <path dest="10" path="19,7,20,30" source="9"/>
            <path dest="11" path="19,7,20,11,23,31" source="9"/>
            <path dest="12" path="19,7,1,27,32" source="9"/>
        </virtualLink>
        <virtualLink bag="32" dest="9,12" id="Designed for Data Flow 63" lmax="917" number="63" responseTime="6762" source="10" lmin="64">
            <path dest="9" path="22,8,18,29" source="10"/>
            <path dest="12" path="22,8,1,27,32" source="10"/>
        </virtualLink>
        <virtualLink bag="64" dest="9,11" id="Designed for Data Flow 64" lmax="1491" number="64" responseTime="5185" source="12" lmin="64">
            <path dest="9" path="28,4,17,29" source="12"/>
            <path dest="11" path="28,16,24,31" source="12"/>
        </virtualLink>
        <virtualLink bag="32" dest="10,12" id="Designed for Data Flow 65" lmax="921" number="65" responseTime="6867" source="9" lmin="64">
            <path dest="10" path="19,7,20,30" source="9"/>
            <path dest="12" path="19,7,1,27,32" source="9"/>
        </virtualLink>
        <virtualLink bag="32" dest="10,11,12" id="Designed for Data Flow 66" lmax="1515" number="66" responseTime="6867" source="9" lmin="64">
            <path dest="10" path="19,7,20,30" source="9"/>
            <path dest="11" path="19,7,9,23,31" source="9"/>
            <path dest="12" path="19,7,1,27,32" source="9"/>
        </virtualLink>
        <virtualLink bag="32" dest="12" id="Designed for Data Flow 67" lmax="816" number="67" responseTime="6762" source="10" lmin="64">
            <path dest="12" path="22,8,1,27,32" source="10"/>
        </virtualLink>
        <virtualLink bag="128" dest="10,11" id="Designed for Data Flow 68" lmax="1485" number="68" responseTime="5778" source="12" lmin="64">
            <path dest="10" path="28,16,10,21,30" source="12"/>
            <path dest="11" path="28,16,24,31" source="12"/>
        </virtualLink>
        <virtualLink bag="64" dest="10,11" id="Designed for Data Flow 69" lmax="1267" number="69" responseTime="7449" source="9" lmin="64">
            <path dest="10" path="19,7,20,30" source="9"/>
            <path dest="11" path="19,7,20,11,23,31" source="9"/>
        </virtualLink>
        <virtualLink bag="16" dest="11,12" id="Designed for Data Flow 70" lmax="1088" number="70" responseTime="7013" source="9" lmin="64">
            <path dest="11" path="19,3,14,24,31" source="9"/>
            <path dest="12" path="19,3,14,26,32" source="9"/>
        </virtualLink>
        <virtualLink bag="128" dest="9,10,12" id="Designed for Data Flow 71" lmax="289" number="71" responseTime="6399" source="11" lmin="64">
            <path dest="9" path="25,15,2,17,29" source="11"/>
            <path dest="10" path="25,15,10,21,30" source="11"/>
            <path dest="12" path="25,15,26,32" source="11"/>
        </virtualLink>
        <virtualLink bag="16" dest="11" id="Designed for Data Flow 72" lmax="1174" number="72" responseTime="5185" source="12" lmin="64">
            <path dest="11" path="28,16,24,31" source="12"/>
        </virtualLink>
        <virtualLink bag="16" dest="9,10,12" id="Designed for Data Flow 73" lmax="1018" number="73" responseTime="6405" source="11" lmin="64">
            <path dest="9" path="25,15,2,17,29" source="11"/>
            <path dest="10" path="25,15,10,21,30" source="11"/>
            <path dest="12" path="25,15,2,27,32" source="11"/>
        </virtualLink>
        <virtualLink bag="32" dest="10,11" id="Designed for Data Flow 74" lmax="869" number="74" responseTime="6799" source="9" lmin="64">
            <path dest="10" path="19,7,20,30" source="9"/>
            <path dest="11" path="19,7,1,14,24,31" source="9"/>
        </virtualLink>
        <virtualLink bag="128" dest="9,10,11" id="Designed for Data Flow 75" lmax="789" number="75" responseTime="5765" source="12" lmin="64">
            <path dest="9" path="28,4,17,29" source="12"/>
            <path dest="10" path="28,4,5,20,30" source="12"/>
            <path dest="11" path="28,4,14,24,31" source="12"/>
        </virtualLink>
        <virtualLink bag="16" dest="9" id="Designed for Data Flow 76" lmax="1042" number="76" responseTime="5510" source="10" lmin="64">
            <path dest="9" path="22,8,18,29" source="10"/>
        </virtualLink>
        <virtualLink bag="16" dest="9" id="Designed for Data Flow 77" lmax="1347" number="77" responseTime="5053" source="12" lmin="64">
            <path dest="9" path="28,4,17,29" source="12"/>
        </virtualLink>
        <virtualLink bag="32" dest="10,11" id="Designed for Data Flow 78" lmax="1252" number="78" responseTime="6634" source="9" lmin="64">
            <path dest="10" path="19,7,20,30" source="9"/>
            <path dest="11" path="19,7,9,23,31" source="9"/>
        </virtualLink>
        <virtualLink bag="128" dest="9,11,12" id="Designed for Data Flow 79" lmax="1456" number="79" responseTime="6762" source="10" lmin="64">
            <path dest="9" path="22,8,18,29" source="10"/>
            <path dest="11" path="22,8,9,23,31" source="10"/>
            <path dest="12" path="22,8,1,27,32" source="10"/>
        </virtualLink>
        <virtualLink bag="32" dest="9,11,12" id="Designed for Data Flow 80" lmax="954" number="80" responseTime="7620" source="10" lmin="64">
            <path dest="9" path="22,8,18,29" source="10"/>
            <path dest="11" path="22,8,9,23,31" source="10"/>
            <path dest="12" path="22,8,9,13,26,32" source="10"/>
        </virtualLink>
        <virtualLink bag="64" dest="9,10,12" id="Designed for Data Flow 81" lmax="1190" number="81" responseTime="6968" source="11" lmin="64">
            <path dest="9" path="25,12,6,18,29" source="11"/>
            <path dest="10" path="25,12,21,30" source="11"/>
            <path dest="12" path="25,12,13,26,32" source="11"/>
        </virtualLink>
        <virtualLink bag="64" dest="9,12" id="Designed for Data Flow 82" lmax="1049" number="82" responseTime="6399" source="11" lmin="64">
            <path dest="9" path="25,15,2,17,29" source="11"/>
            <path dest="12" path="25,15,26,32" source="11"/>
        </virtualLink>
        <virtualLink bag="16" dest="11,12" id="Designed for Data Flow 83" lmax="1039" number="83" responseTime="8449" source="10" lmin="64">
            <path dest="11" path="22,11,23,31" source="10"/>
            <path dest="12" path="22,11,23,15,26,32" source="10"/>
        </virtualLink>
        <virtualLink bag="16" dest="10,11,12" id="Designed for Data Flow 84" lmax="1236" number="84" responseTime="8541" source="9" lmin="64">
            <path dest="10" path="19,7,20,30" source="9"/>
            <path dest="11" path="19,7,20,11,23,31" source="9"/>
            <path dest="12" path="19,7,20,11,13,26,32" source="9"/>
        </virtualLink>
        <virtualLink bag="16" dest="9,10,12" id="Designed for Data Flow 85" lmax="1507" number="85" responseTime="6967" source="11" lmin="64">
            <path dest="9" path="25,12,6,18,29" source="11"/>
            <path dest="10" path="25,12,6,20,30" source="11"/>
            <path dest="12" path="25,12,13,26,32" source="11"/>
        </virtualLink>
        <virtualLink bag="64" dest="10,11" id="Designed for Data Flow 86" lmax="1273" number="86" responseTime="5778" source="12" lmin="64">
            <path dest="10" path="28,16,10,21,30" source="12"/>
            <path dest="11" path="28,16,24,31" source="12"/>
        </virtualLink>
        <virtualLink bag="32" dest="9,10,12" id="Designed for Data Flow 87" lmax="1365" number="87" responseTime="7754" source="11" lmin="64">
            <path dest="9" path="25,12,6,18,29" source="11"/>
            <path dest="10" path="25,12,21,30" source="11"/>
            <path dest="12" path="25,12,6,18,3,27,32" source="11"/>
        </virtualLink>
        <virtualLink bag="32" dest="11,12" id="Designed for Data Flow 88" lmax="1371" number="88" responseTime="7363" source="10" lmin="64">
            <path dest="11" path="22,11,23,31" source="10"/>
            <path dest="12" path="22,11,13,26,32" source="10"/>
        </virtualLink>
        <virtualLink bag="16" dest="9,10,11" id="Designed for Data Flow 89" lmax="1081" number="89" responseTime="5766" source="12" lmin="64">
            <path dest="9" path="28,4,17,29" source="12"/>
            <path dest="10" path="28,4,5,20,30" source="12"/>
            <path dest="11" path="28,4,14,24,31" source="12"/>
        </virtualLink>
        <virtualLink bag="16" dest="9,10" id="Designed for Data Flow 90" lmax="914" number="90" responseTime="6223" source="11" lmin="64">
            <path dest="9" path="25,15,2,17,29" source="11"/>
            <path dest="10" path="25,15,10,21,30" source="11"/>
        </virtualLink>
        <virtualLink bag="16" dest="12" id="Designed for Data Flow 91" lmax="1074" number="91" responseTime="6399" source="11" lmin="64">
            <path dest="12" path="25,15,26,32" source="11"/>
        </virtualLink>
        <virtualLink bag="32" dest="10,11" id="Designed for Data Flow 92" lmax="1135" number="92" responseTime="6634" source="9" lmin="64">
            <path dest="10" path="19,7,20,30" source="9"/>
            <path dest="11" path="19,7,9,23,31" source="9"/>
        </virtualLink>
        <virtualLink bag="32" dest="12" id="Designed for Data Flow 93" lmax="1014" number="93" responseTime="6399" source="11" lmin="64">
            <path dest="12" path="25,15,26,32" source="11"/>
        </virtualLink>
        <virtualLink bag="16" dest="9,11" id="Designed for Data Flow 94" lmax="1123" number="94" responseTime="6529" source="10" lmin="64">
            <path dest="9" path="22,8,18,29" source="10"/>
            <path dest="11" path="22,8,9,23,31" source="10"/>
        </virtualLink>
        <virtualLink bag="64" dest="9,11,12" id="Designed for Data Flow 95" lmax="1425" number="95" responseTime="7621" source="10" lmin="64">
            <path dest="9" path="22,8,18,29" source="10"/>
            <path dest="11" path="22,8,9,23,31" source="10"/>
            <path dest="12" path="22,8,9,13,26,32" source="10"/>
        </virtualLink>
        <virtualLink bag="32" dest="11,12" id="Designed for Data Flow 96" lmax="880" number="96" responseTime="7363" source="10" lmin="64">
            <path dest="11" path="22,11,23,31" source="10"/>
            <path dest="12" path="22,11,13,26,32" source="10"/>
        </virtualLink>
        <virtualLink bag="128" dest="12" id="Designed for Data Flow 97" lmax="1502" number="97" responseTime="6762" source="10" lmin="64">
            <path dest="12" path="22,8,1,27,32" source="10"/>
        </virtualLink>
        <virtualLink bag="16" dest="10,11,12" id="Designed for Data Flow 98" lmax="949" number="98" responseTime="7726" source="9" lmin="64">
            <path dest="10" path="19,7,20,30" source="9"/>
            <path dest="11" path="19,7,9,23,31" source="9"/>
            <path dest="12" path="19,7,9,13,26,32" source="9"/>
        </virtualLink>
        <virtualLink bag="32" dest="9,10" id="Designed for Data Flow 99" lmax="1432" number="99" responseTime="5765" source="11" lmin="64">
            <path dest="9" path="25,12,6,18,29" source="11"/>
            <path dest="10" path="25,12,21,30" source="11"/>
        </virtualLink>
        <virtualLink bag="32" dest="9,10" id="Designed for Data Flow 100" lmax="811" number="100" responseTime="5765" source="11" lmin="64">
            <path dest="9" path="25,12,6,18,29" source="11"/>
            <path dest="10" path="25,12,21,30" source="11"/>
        </virtualLink>
    </virtualLinks>
    <dataFlows>
        <dataFlow dest="14" id="Data Flow 1" jMax="0" msgSize="22432" period="16461" source="15" tMax="49095" vl="1"/>
        <dataFlow dest="16" id="Data Flow 2" jMax="0" msgSize="761730" period="18072" source="13" tMax="90312" vl="2"/>
        <dataFlow dest="16,15" id="Data Flow 3" jMax="0" msgSize="914737" period="17117" source="13" tMax="71408" vl="3"/>
        <dataFlow dest="16,13,15" id="Data Flow 4" jMax="0" msgSize="622635" period="13176" source="14" tMax="26380" vl="4"/>
        <dataFlow dest="16,14,15" id="Data Flow 5" jMax="0" msgSize="377308" period="14876" source="13" tMax="21916" vl="5"/>
        <dataFlow dest="14,13" id="Data Flow 6" jMax="0" msgSize="99369" period="18438" source="15" tMax="82581" vl="6"/>
        <dataFlow dest="15,13,16" id="Data Flow 7" jMax="0" msgSize="46653" period="13838" source="14" tMax="96822" vl="7"/>
        <dataFlow dest="16" id="Data Flow 8" jMax="0" msgSize="476313" period="18901" source="13" tMax="32300" vl="8"/>
        <dataFlow dest="16" id="Data Flow 9" jMax="0" msgSize="613979" period="16850" source="13" tMax="82438" vl="9"/>
        <dataFlow dest="15" id="Data Flow 10" jMax="0" msgSize="699245" period="18594" source="14" tMax="69569" vl="10"/>
        <dataFlow dest="13,16" id="Data Flow 11" jMax="0" msgSize="491946" period="14228" source="15" tMax="86288" vl="11"/>
        <dataFlow dest="14,15,13" id="Data Flow 12" jMax="0" msgSize="179554" period="15664" source="16" tMax="76811" vl="12"/>
        <dataFlow dest="14" id="Data Flow 13" jMax="0" msgSize="226320" period="18167" source="15" tMax="37377" vl="13"/>
        <dataFlow dest="13,14" id="Data Flow 14" jMax="0" msgSize="584796" period="15469" source="16" tMax="24655" vl="14"/>
        <dataFlow dest="14,13" id="Data Flow 15" jMax="0" msgSize="991508" period="18036" source="16" tMax="68104" vl="15"/>
        <dataFlow dest="13,14" id="Data Flow 16" jMax="0" msgSize="647151" period="19469" source="16" tMax="61735" vl="16"/>
        <dataFlow dest="15" id="Data Flow 17" jMax="0" msgSize="757902" period="19621" source="13" tMax="47585" vl="17"/>
        <dataFlow dest="13" id="Data Flow 18" jMax="0" msgSize="547335" period="16898" source="15" tMax="43562" vl="18"/>
        <dataFlow dest="14,15" id="Data Flow 19" jMax="0" msgSize="271818" period="18978" source="13" tMax="30964" vl="19"/>
        <dataFlow dest="13,14,15" id="Data Flow 20" jMax="0" msgSize="810674" period="10551" source="16" tMax="25001" vl="20"/>
        <dataFlow dest="14" id="Data Flow 21" jMax="0" msgSize="701981" period="19521" source="16" tMax="93258" vl="21"/>
        <dataFlow dest="15" id="Data Flow 22" jMax="0" msgSize="867861" period="11096" source="14" tMax="77761" vl="22"/>
        <dataFlow dest="16" id="Data Flow 23" jMax="0" msgSize="718285" period="12275" source="13" tMax="51791" vl="23"/>
        <dataFlow dest="16,13" id="Data Flow 24" jMax="0" msgSize="594978" period="16209" source="15" tMax="21684" vl="24"/>
        <dataFlow dest="14,16" id="Data Flow 25" jMax="0" msgSize="992426" period="16803" source="15" tMax="30811" vl="25"/>
        <dataFlow dest="14" id="Data Flow 26" jMax="0" msgSize="426924" period="12815" source="16" tMax="90972" vl="26"/>
        <dataFlow dest="16,13,14" id="Data Flow 27" jMax="0" msgSize="571023" period="19737" source="15" tMax="92962" vl="27"/>
        <dataFlow dest="13" id="Data Flow 28" jMax="0" msgSize="804340" period="13081" source="14" tMax="91930" vl="28"/>
        <dataFlow dest="13" id="Data Flow 29" jMax="0" msgSize="63876" period="11391" source="15" tMax="98952" vl="29"/>
        <dataFlow dest="13,15" id="Data Flow 30" jMax="0" msgSize="112583" period="13959" source="14" tMax="49484" vl="30"/>
        <dataFlow dest="15,16" id="Data Flow 31" jMax="0" msgSize="653109" period="13112" source="14" tMax="82238" vl="31"/>
        <dataFlow dest="16,15,14" id="Data Flow 32" jMax="0" msgSize="906249" period="10098" source="13" tMax="46496" vl="32"/>
        <dataFlow dest="13" id="Data Flow 33" jMax="0" msgSize="277747" period="10052" source="16" tMax="91092" vl="33"/>
        <dataFlow dest="15,16" id="Data Flow 34" jMax="0" msgSize="57696" period="13458" source="14" tMax="86411" vl="34"/>
        <dataFlow dest="13,15,16" id="Data Flow 35" jMax="0" msgSize="744826" period="13108" source="14" tMax="97368" vl="35"/>
        <dataFlow dest="14,15,16" id="Data Flow 36" jMax="0" msgSize="86155" period="17049" source="13" tMax="24176" vl="36"/>
        <dataFlow dest="15,13" id="Data Flow 37" jMax="0" msgSize="257295" period="10129" source="16" tMax="35630" vl="37"/>
        <dataFlow dest="13,15" id="Data Flow 38" jMax="0" msgSize="956354" period="11035" source="16" tMax="46784" vl="38"/>
        <dataFlow dest="16,14" id="Data Flow 39" jMax="0" msgSize="701775" period="12846" source="15" tMax="35132" vl="39"/>
        <dataFlow dest="13,15" id="Data Flow 40" jMax="0" msgSize="662564" period="19811" source="16" tMax="24588" vl="40"/>
        <dataFlow dest="15,13" id="Data Flow 41" jMax="0" msgSize="794164" period="15980" source="16" tMax="35587" vl="41"/>
        <dataFlow dest="16,15,14" id="Data Flow 42" jMax="0" msgSize="85917" period="17638" source="13" tMax="67406" vl="42"/>
        <dataFlow dest="14,15,13" id="Data Flow 43" jMax="0" msgSize="251196" period="13349" source="16" tMax="52637" vl="43"/>
        <dataFlow dest="13,15" id="Data Flow 44" jMax="0" msgSize="462397" period="15341" source="16" tMax="97943" vl="44"/>
        <dataFlow dest="16" id="Data Flow 45" jMax="0" msgSize="822459" period="14781" source="14" tMax="78694" vl="45"/>
        <dataFlow dest="13" id="Data Flow 46" jMax="0" msgSize="988450" period="10705" source="15" tMax="27016" vl="46"/>
        <dataFlow dest="16" id="Data Flow 47" jMax="0" msgSize="177000" period="18292" source="15" tMax="81671" vl="47"/>
        <dataFlow dest="16" id="Data Flow 48" jMax="0" msgSize="362652" period="18621" source="14" tMax="30461" vl="48"/>
        <dataFlow dest="13,14,16" id="Data Flow 49" jMax="0" msgSize="513740" period="12290" source="15" tMax="90020" vl="49"/>
        <dataFlow dest="15,16" id="Data Flow 50" jMax="0" msgSize="570414" period="12767" source="13" tMax="64143" vl="50"/>
        <dataFlow dest="15,14" id="Data Flow 51" jMax="0" msgSize="457094" period="16047" source="13" tMax="93676" vl="51"/>
        <dataFlow dest="16" id="Data Flow 52" jMax="0" msgSize="616622" period="10287" source="15" tMax="82945" vl="52"/>
        <dataFlow dest="15,13,16" id="Data Flow 53" jMax="0" msgSize="420090" period="15779" source="14" tMax="84403" vl="53"/>
        <dataFlow dest="13,14,16" id="Data Flow 54" jMax="0" msgSize="886955" period="10110" source="15" tMax="86445" vl="54"/>
        <dataFlow dest="16,15,14" id="Data Flow 55" jMax="0" msgSize="989534" period="17537" source="13" tMax="77601" vl="55"/>
        <dataFlow dest="14,15" id="Data Flow 56" jMax="0" msgSize="237724" period="17278" source="16" tMax="85075" vl="56"/>
        <dataFlow dest="15,13,16" id="Data Flow 57" jMax="0" msgSize="796226" period="16999" source="14" tMax="76603" vl="57"/>
        <dataFlow dest="14,16" id="Data Flow 58" jMax="0" msgSize="583911" period="16692" source="15" tMax="20418" vl="58"/>
        <dataFlow dest="15,13" id="Data Flow 59" jMax="0" msgSize="748756" period="13656" source="16" tMax="31525" vl="59"/>
        <dataFlow dest="15,16" id="Data Flow 60" jMax="0" msgSize="287478" period="13512" source="14" tMax="53410" vl="60"/>
        <dataFlow dest="14,15,16" id="Data Flow 61" jMax="0" msgSize="228936" period="13302" source="13" tMax="46605" vl="61"/>
        <dataFlow dest="16,14,15" id="Data Flow 62" jMax="0" msgSize="773219" period="18077" source="13" tMax="79338" vl="62"/>
        <dataFlow dest="16,13" id="Data Flow 63" jMax="0" msgSize="414590" period="15286" source="14" tMax="47198" vl="63"/>
        <dataFlow dest="13,15" id="Data Flow 64" jMax="0" msgSize="350708" period="15564" source="16" tMax="23618" vl="64"/>
        <dataFlow dest="16,14" id="Data Flow 65" jMax="0" msgSize="457019" period="16760" source="13" tMax="38270" vl="65"/>
        <dataFlow dest="15,14,16" id="Data Flow 66" jMax="0" msgSize="755778" period="16510" source="13" tMax="85162" vl="66"/>
        <dataFlow dest="16" id="Data Flow 67" jMax="0" msgSize="440564" period="18342" source="14" tMax="83831" vl="67"/>
        <dataFlow dest="15,14" id="Data Flow 68" jMax="0" msgSize="212777" period="18953" source="16" tMax="62262" vl="68"/>
        <dataFlow dest="15,14" id="Data Flow 69" jMax="0" msgSize="236645" period="12424" source="13" tMax="38710" vl="69"/>
        <dataFlow dest="15,16" id="Data Flow 70" jMax="0" msgSize="934673" period="14377" source="13" tMax="63651" vl="70"/>
        <dataFlow dest="16,14,13" id="Data Flow 71" jMax="0" msgSize="21742" period="11536" source="15" tMax="66044" vl="71"/>
        <dataFlow dest="15" id="Data Flow 72" jMax="0" msgSize="769648" period="10931" source="16" tMax="64565" vl="72"/>
        <dataFlow dest="16,14,13" id="Data Flow 73" jMax="0" msgSize="857650" period="14153" source="15" tMax="35280" vl="73"/>
        <dataFlow dest="14,15" id="Data Flow 74" jMax="0" msgSize="400844" period="15631" source="13" tMax="53892" vl="74"/>
        <dataFlow dest="15,14,13" id="Data Flow 75" jMax="0" msgSize="71919" period="12474" source="16" tMax="90309" vl="75"/>
        <dataFlow dest="13" id="Data Flow 76" jMax="0" msgSize="699818" period="11266" source="14" tMax="74592" vl="76"/>
        <dataFlow dest="13" id="Data Flow 77" jMax="0" msgSize="861663" period="10614" source="16" tMax="95100" vl="77"/>
        <dataFlow dest="14,15" id="Data Flow 78" jMax="0" msgSize="576883" period="15334" source="13" tMax="99789" vl="78"/>
        <dataFlow dest="15,16,13" id="Data Flow 79" jMax="0" msgSize="191530" period="17464" source="14" tMax="90401" vl="79"/>
        <dataFlow dest="16,13,15" id="Data Flow 80" jMax="0" msgSize="494282" period="17464" source="14" tMax="71644" vl="80"/>
        <dataFlow dest="16,13,14" id="Data Flow 81" jMax="0" msgSize="254814" period="14307" source="15" tMax="25099" vl="81"/>
        <dataFlow dest="16,13" id="Data Flow 82" jMax="0" msgSize="175256" period="11239" source="15" tMax="90007" vl="82"/>
        <dataFlow dest="16,15" id="Data Flow 83" jMax="0" msgSize="766167" period="12383" source="14" tMax="52355" vl="83"/>
        <dataFlow dest="16,15,14" id="Data Flow 84" jMax="0" msgSize="835387" period="11263" source="13" tMax="50599" vl="84"/>
        <dataFlow dest="16,13,14" id="Data Flow 85" jMax="0" msgSize="944140" period="10355" source="15" tMax="52971" vl="85"/>
        <dataFlow dest="14,15" id="Data Flow 86" jMax="0" msgSize="275732" period="14416" source="16" tMax="56277" vl="86"/>
        <dataFlow dest="14,13,16" id="Data Flow 87" jMax="0" msgSize="780081" period="18958" source="15" tMax="40158" vl="87"/>
        <dataFlow dest="16,15" id="Data Flow 88" jMax="0" msgSize="552066" period="13349" source="14" tMax="39219" vl="88"/>
        <dataFlow dest="15,13,14" id="Data Flow 89" jMax="0" msgSize="765915" period="11856" source="16" tMax="50050" vl="89"/>
        <dataFlow dest="14,13" id="Data Flow 90" jMax="0" msgSize="922106" period="17024" source="15" tMax="60009" vl="90"/>
        <dataFlow dest="16" id="Data Flow 91" jMax="0" msgSize="868800" period="13543" source="15" tMax="39757" vl="91"/>
        <dataFlow dest="15,14" id="Data Flow 92" jMax="0" msgSize="585258" period="17231" source="13" tMax="93782" vl="92"/>
        <dataFlow dest="16" id="Data Flow 93" jMax="0" msgSize="395434" period="13100" source="15" tMax="52689" vl="93"/>
        <dataFlow dest="15,13" id="Data Flow 94" jMax="0" msgSize="699168" period="10410" source="14" tMax="28175" vl="94"/>
        <dataFlow dest="13,16,15" id="Data Flow 95" jMax="0" msgSize="356652" period="16627" source="14" tMax="78740" vl="95"/>
        <dataFlow dest="16,15" id="Data Flow 96" jMax="0" msgSize="396260" period="15247" source="14" tMax="91645" vl="96"/>
        <dataFlow dest="16" id="Data Flow 97" jMax="0" msgSize="136737" period="12083" source="14" tMax="32008" vl="97"/>
        <dataFlow dest="16,14,15" id="Data Flow 98" jMax="0" msgSize="935630" period="16609" source="13" tMax="77853" vl="98"/>
        <dataFlow dest="14,13" id="Data Flow 99" jMax="0" msgSize="577359" period="13344" source="15" tMax="94967" vl="99"/>
        <dataFlow dest="14,13" id="Data Flow 100" jMax="0" msgSize="442993" period="18571" source="15" tMax="80412" vl="100"/>
    </dataFlows>
</afdxxml>
